{
  "type": "Feature",
  "properties": {
    "gn:admin1_code":"C",
    "gn:admin2_code":"16.0",
    "gn:asciiname":"Massasa",
    "gn:country_code":"MW",
    "gn:dem":1540,
    "gn:feature_class":"P",
    "gn:feature_code":"PPL",
    "gn:name":"Massasa",
    "gn:population":0,
    "gn:timezone":"Africa/Blantyre",
    "iso:country":"MW",
    "name:und_x_variant":[
        "Masasa",
        "Massasa"
    ],
    "wof:name":"Massasa",
    "wof:placetype":"locality"
},
  "geometry": {"coordinates":[34.43316,-14.4359],"type":"Point"}
}