{
  "type": "Feature",
  "properties": {
    "gn:admin1_code":"S",
    "gn:admin2_code":"2.0",
    "gn:asciiname":"Thomas",
    "gn:country_code":"MW",
    "gn:dem":162,
    "gn:feature_class":"P",
    "gn:feature_code":"PPL",
    "gn:name":"Thomas",
    "gn:population":0,
    "gn:timezone":"Africa/Blantyre",
    "iso:country":"MW",
    "name:ara_x_preferred":[
        "\u062a\u0648\u0645\u0627\u0633"
    ],
    "name:arc_x_preferred":[
        "\u072c\u0710\u0718\u0721\u0710"
    ],
    "name:bre_x_preferred":[
        "Thomas"
    ],
    "name:cat_x_preferred":[
        "Thomas"
    ],
    "name:ceb_x_preferred":[
        "Thomas"
    ],
    "name:ces_x_preferred":[
        "Thomas"
    ],
    "name:deu_x_preferred":[
        "Thomas"
    ],
    "name:ell_x_preferred":[
        "\u0398\u03c9\u03bc\u03ac\u03c2"
    ],
    "name:est_x_preferred":[
        "Thomas"
    ],
    "name:fin_x_preferred":[
        "Thomas"
    ],
    "name:fra_x_preferred":[
        "Thomas"
    ],
    "name:fry_x_preferred":[
        "Thomas"
    ],
    "name:heb_x_preferred":[
        "\u05ea\u05d5\u05de\u05d0\u05e1"
    ],
    "name:hye_x_preferred":[
        "\u0539\u0578\u0574\u0561\u057d"
    ],
    "name:ita_x_preferred":[
        "Thomas"
    ],
    "name:jpn_x_preferred":[
        "\u30c8\u30de\u30b9"
    ],
    "name:kor_x_preferred":[
        "\ud1a0\uba38\uc2a4"
    ],
    "name:lav_x_preferred":[
        "Thomas"
    ],
    "name:lit_x_preferred":[
        "Thomas"
    ],
    "name:nds_x_preferred":[
        "Thomas"
    ],
    "name:nld_x_preferred":[
        "Thomas"
    ],
    "name:pol_x_preferred":[
        "Thomas"
    ],
    "name:por_x_preferred":[
        "Thomas"
    ],
    "name:rus_x_preferred":[
        "Thomas"
    ],
    "name:spa_x_preferred":[
        "Thomas"
    ],
    "name:swe_x_preferred":[
        "Thomas"
    ],
    "name:tel_x_preferred":[
        "\u0c25\u0c3e\u0c2e\u0c38\u0c4d"
    ],
    "name:ukr_x_preferred":[
        "\u0422\u043e\u043c\u0430\u0441"
    ],
    "name:vie_x_preferred":[
        "Thomas"
    ],
    "name:vol_x_preferred":[
        "Thomas"
    ],
    "name:zho_x_preferred":[
        "\u6258\u9a6c\u65af"
    ],
    "wof:name":"Thomas",
    "wof:placetype":"locality"
},
  "geometry": {"coordinates":[34.55,-16.08333],"type":"Point"}
}