{
  "type": "Feature",
  "properties": {
    "gn:admin1_code":"C",
    "gn:admin2_code":"11.0",
    "gn:asciiname":"Lumbadzi",
    "gn:country_code":"MW",
    "gn:dem":1206,
    "gn:feature_class":"P",
    "gn:feature_code":"PPL",
    "gn:name":"Lumbadzi",
    "gn:population":0,
    "gn:timezone":"Africa/Blantyre",
    "iso:country":"MW",
    "name:und_x_variant":[
        "Lombadzi",
        "Lumbadzi"
    ],
    "wof:name":"Lumbadzi",
    "wof:placetype":"locality"
},
  "geometry": {"coordinates":[33.81678,-13.77008],"type":"Point"}
}