{
  "type": "Feature",
  "properties": {
    "gn:admin1_code":"C",
    "gn:admin2_code":"16.0",
    "gn:asciiname":"Zidana",
    "gn:country_code":"MW",
    "gn:dem":937,
    "gn:feature_class":"P",
    "gn:feature_code":"PPL",
    "gn:name":"Zidana",
    "gn:population":0,
    "gn:timezone":"Africa/Blantyre",
    "iso:country":"MW",
    "wof:name":"Zidana",
    "wof:placetype":"locality"
},
  "geometry": {"coordinates":[34.74308,-14.85228],"type":"Point"}
}