{
  "type": "Feature",
  "properties": {
    "gn:admin1_code":"C",
    "gn:admin2_code":"22.0",
    "gn:asciiname":"Mpuwa",
    "gn:country_code":"MW",
    "gn:dem":478,
    "gn:feature_class":"P",
    "gn:feature_code":"PPL",
    "gn:name":"Mpuwa",
    "gn:population":0,
    "gn:timezone":"Africa/Blantyre",
    "iso:country":"MW",
    "wof:name":"Mpuwa",
    "wof:placetype":"locality"
},
  "geometry": {"coordinates":[34.38333,-13.53333],"type":"Point"}
}