{
  "type": "Feature",
  "properties": {
    "gn:admin1_code":"S",
    "gn:admin2_code":"2.0",
    "gn:asciiname":"Mwiza",
    "gn:country_code":"MW",
    "gn:dem":100,
    "gn:feature_class":"P",
    "gn:feature_code":"PPL",
    "gn:name":"Mwiza",
    "gn:population":0,
    "gn:timezone":"Africa/Blantyre",
    "iso:country":"MW",
    "name:und_x_variant":[
        "Mwita",
        "Mwiza"
    ],
    "wof:name":"Mwiza",
    "wof:placetype":"locality"
},
  "geometry": {"coordinates":[34.81657,-16.04429],"type":"Point"}
}