{
  "type": "Feature",
  "properties": {
    "gn:admin1_code":"N",
    "gn:admin2_code":"15.0",
    "gn:asciiname":"Ndakhara Chavinda",
    "gn:country_code":"MW",
    "gn:dem":1153,
    "gn:feature_class":"P",
    "gn:feature_code":"PPL",
    "gn:name":"Ndakhara Chavinda",
    "gn:population":0,
    "gn:timezone":"Africa/Blantyre",
    "iso:country":"MW",
    "wof:name":"Ndakhara Chavinda",
    "wof:placetype":"locality"
},
  "geometry": {"coordinates":[33.2751,-11.5755],"type":"Point"}
}