{
  "type": "Feature",
  "properties": {
    "gn:admin1_code":"N",
    "gn:admin2_code":"17.0",
    "gn:asciiname":"Longwe",
    "gn:country_code":"MW",
    "gn:dem":537,
    "gn:feature_class":"P",
    "gn:feature_code":"PPL",
    "gn:name":"Longwe",
    "gn:population":0,
    "gn:timezone":"Africa/Blantyre",
    "iso:country":"MW",
    "wof:name":"Longwe",
    "wof:placetype":"locality"
},
  "geometry": {"coordinates":[34.23333,-11.76667],"type":"Point"}
}