{
  "type": "Feature",
  "properties": {
    "gn:admin1_code":"S",
    "gn:admin2_code":"24.0",
    "gn:asciiname":"Makala",
    "gn:country_code":"MW",
    "gn:dem":770,
    "gn:feature_class":"P",
    "gn:feature_code":"PPL",
    "gn:name":"Makala",
    "gn:population":0,
    "gn:timezone":"Africa/Blantyre",
    "iso:country":"MW",
    "name:eus_x_preferred":[
        "Makala"
    ],
    "name:fra_x_preferred":[
        "Makala"
    ],
    "name:lin_x_preferred":[
        "Mak\u00e1la"
    ],
    "name:pol_x_preferred":[
        "Makala"
    ],
    "wof:name":"Makala",
    "wof:placetype":"locality"
},
  "geometry": {"coordinates":[35.0922,-15.61609],"type":"Point"}
}