{
  "type": "Feature",
  "properties": {
    "gn:admin1_code":"S",
    "gn:admin2_code":"31.0",
    "gn:asciiname":"Neno",
    "gn:country_code":"MW",
    "gn:dem":907,
    "gn:feature_class":"P",
    "gn:feature_code":"PPLA2",
    "gn:name":"Neno",
    "gn:population":0,
    "gn:timezone":"Africa/Blantyre",
    "iso:country":"MW",
    "name:heb_x_preferred":[
        "\u05e0\u05e0\u05d5"
    ],
    "name:hun_x_preferred":[
        "Neno"
    ],
    "name:zho_cn_x_preferred":[
        "\u5c3c\u8bfa"
    ],
    "name:zho_tw_x_preferred":[
        "\u5c3c\u8afe"
    ],
    "wof:name":"Neno",
    "wof:placetype":"locality"
},
  "geometry": {"coordinates":[34.65343,-15.39805],"type":"Point"}
}