{
  "type": "Feature",
  "properties": {
    "gn:admin1_code":"N",
    "gn:admin2_code":"15.0",
    "gn:asciiname":"Samuel Jere",
    "gn:country_code":"MW",
    "gn:dem":1261,
    "gn:feature_class":"P",
    "gn:feature_code":"PPL",
    "gn:name":"Samuel Jere",
    "gn:population":0,
    "gn:timezone":"Africa/Blantyre",
    "iso:country":"MW",
    "wof:name":"Samuel Jere",
    "wof:placetype":"locality"
},
  "geometry": {"coordinates":[33.66667,-11.33333],"type":"Point"}
}