{
  "type": "Feature",
  "properties": {
    "gn:admin1_code":"S",
    "gn:admin2_code":"29.0",
    "gn:asciiname":"Dyanyama",
    "gn:country_code":"MW",
    "gn:dem":711,
    "gn:feature_class":"P",
    "gn:feature_code":"PPL",
    "gn:name":"Dyanyama",
    "gn:population":0,
    "gn:timezone":"Africa/Blantyre",
    "iso:country":"MW",
    "wof:name":"Dyanyama",
    "wof:placetype":"locality"
},
  "geometry": {"coordinates":[35.43589,-15.67577],"type":"Point"}
}