{
  "type": "Feature",
  "properties": {
    "gn:admin1_code":"N",
    "gn:admin2_code":"15.0",
    "gn:asciiname":"Daniel Muwowo",
    "gn:country_code":"MW",
    "gn:dem":1218,
    "gn:feature_class":"P",
    "gn:feature_code":"PPL",
    "gn:name":"Daniel Muwowo",
    "gn:population":0,
    "gn:timezone":"Africa/Blantyre",
    "iso:country":"MW",
    "wof:name":"Daniel Muwowo",
    "wof:placetype":"locality"
},
  "geometry": {"coordinates":[33.41245,-11.75462],"type":"Point"}
}