{
  "type": "Feature",
  "properties": {
    "gn:admin1_code":"C",
    "gn:admin2_code":"13.0",
    "gn:asciiname":"Chiti",
    "gn:country_code":"MW",
    "gn:dem":1102,
    "gn:feature_class":"P",
    "gn:feature_code":"PPL",
    "gn:name":"Chiti",
    "gn:population":0,
    "gn:timezone":"Africa/Blantyre",
    "iso:country":"MW",
    "name:ceb_x_preferred":[
        "Chiti"
    ],
    "name:fra_x_preferred":[
        "Chiti"
    ],
    "name:mai_x_preferred":[
        "\u091a\u093f\u0924\u0940"
    ],
    "name:msa_x_preferred":[
        "Chiti"
    ],
    "name:nep_x_preferred":[
        "\u091a\u093f\u0924\u0940"
    ],
    "name:new_x_preferred":[
        "\u091a\u093f\u0924\u0940"
    ],
    "name:pol_x_preferred":[
        "Chiti"
    ],
    "wof:name":"Chiti",
    "wof:placetype":"locality"
},
  "geometry": {"coordinates":[33.02341,-13.64628],"type":"Point"}
}