{
  "type": "Feature",
  "properties": {
    "gn:admin1_code":"N",
    "gn:admin2_code":"15.0",
    "gn:asciiname":"Zwayumbo Makamo",
    "gn:country_code":"MW",
    "gn:dem":1241,
    "gn:feature_class":"P",
    "gn:feature_code":"PPL",
    "gn:name":"Zwayumbo Makamo",
    "gn:population":0,
    "gn:timezone":"Africa/Blantyre",
    "iso:country":"MW",
    "wof:name":"Zwayumbo Makamo",
    "wof:placetype":"locality"
},
  "geometry": {"coordinates":[33.46024,-11.85],"type":"Point"}
}