{
  "type": "Feature",
  "properties": {
    "iso:country":"MW",
    "name:azb_x_preferred":[
        "\u0686\u06cc\u0646 \u062a\u0686\u0647"
    ],
    "name:eng_x_preferred":[
        "Chintheche"
    ],
    "name:fas_x_preferred":[
        "\u0686\u06cc\u0646 \u062a\u0686\u0647"
    ],
    "name:fra_x_preferred":[
        "Chintheche"
    ],
    "name:nld_x_preferred":[
        "Chintheche"
    ],
    "name:nya_x_preferred":[
        "Chintheche"
    ],
    "name:und_x_variant":[
        "Chinteche"
    ],
    "name:zul_x_preferred":[
        "Chintheche"
    ],
    "qs:gn_country":"MW",
    "qs:gn_fcode":"PPL",
    "qs:gn_pop":0,
    "qs:name":"Chintheche",
    "qs:name_adm0":"Malawi",
    "qs:name_adm1":"Nkhata Bay",
    "qs:photos":58,
    "qs:photos_1k":12,
    "qs:photos_9k":1,
    "qs:photos_9r":2,
    "qs:photos_all":58,
    "qs:photos_sr":2,
    "qs:placetype":"Town",
    "qs:pop_sr":"4",
    "qs:woe_adm0":23424889,
    "wd:wordcount":376,
    "wof:name":"Chintheche",
    "wof:placetype":"locality"
},
  "geometry": {"coordinates":[34.16938,-11.8248],"type":"Point"}
}