{
  "type": "Feature",
  "properties": {
    "gn:admin1_code":"N",
    "gn:admin2_code":"15.0",
    "gn:asciiname":"Perekamoyo Chima",
    "gn:country_code":"MW",
    "gn:dem":1257,
    "gn:feature_class":"P",
    "gn:feature_code":"PPL",
    "gn:name":"Perekamoyo Chima",
    "gn:population":0,
    "gn:timezone":"Africa/Blantyre",
    "iso:country":"MW",
    "wof:name":"Perekamoyo Chima",
    "wof:placetype":"locality"
},
  "geometry": {"coordinates":[33.68333,-11.43333],"type":"Point"}
}