{
  "type": "Feature",
  "properties": {
    "gn:admin1_code":"N",
    "gn:admin2_code":"17.0",
    "gn:asciiname":"Mbwawa",
    "gn:country_code":"MW",
    "gn:dem":481,
    "gn:feature_class":"P",
    "gn:feature_code":"PPL",
    "gn:name":"Mbwawa",
    "gn:population":0,
    "gn:timezone":"Africa/Blantyre",
    "iso:country":"MW",
    "wof:name":"Mbwawa",
    "wof:placetype":"locality"
},
  "geometry": {"coordinates":[34.21667,-11.23333],"type":"Point"}
}