{
  "type": "Feature",
  "properties": {
    "gn:admin1_code":"N",
    "gn:admin2_code":"17.0",
    "gn:asciiname":"Chitete",
    "gn:country_code":"MW",
    "gn:dem":490,
    "gn:feature_class":"P",
    "gn:feature_code":"PPL",
    "gn:name":"Chitete",
    "gn:population":0,
    "gn:timezone":"Africa/Blantyre",
    "iso:country":"MW",
    "name:swa_x_preferred":[
        "Chitete"
    ],
    "wof:name":"Chitete",
    "wof:placetype":"locality"
},
  "geometry": {"coordinates":[34.02047,-12.19048],"type":"Point"}
}