{
  "type": "Feature",
  "properties": {
    "gn:admin1_code":"N",
    "gn:admin2_code":"17.0",
    "gn:asciiname":"Zayuka",
    "gn:country_code":"MW",
    "gn:dem":494,
    "gn:feature_class":"P",
    "gn:feature_code":"PPL",
    "gn:name":"Zayuka",
    "gn:population":0,
    "gn:timezone":"Africa/Blantyre",
    "iso:country":"MW",
    "wof:name":"Zayuka",
    "wof:placetype":"locality"
},
  "geometry": {"coordinates":[34.20748,-11.71742],"type":"Point"}
}