{
  "type": "Feature",
  "properties": {
    "gn:admin1_code":"N",
    "gn:admin2_code":"21.0",
    "gn:asciiname":"Mwahangula",
    "gn:country_code":"MW",
    "gn:dem":1472,
    "gn:feature_class":"P",
    "gn:feature_code":"PPL",
    "gn:name":"Mwahangula",
    "gn:population":0,
    "gn:timezone":"Africa/Blantyre",
    "iso:country":"MW",
    "wof:name":"Mwahangula",
    "wof:placetype":"locality"
},
  "geometry": {"coordinates":[33.8496,-10.91104],"type":"Point"}
}