{
  "type": "Feature",
  "properties": {
    "gn:admin1_code":"S",
    "gn:admin2_code":"31.0",
    "gn:asciiname":"Cassapa",
    "gn:country_code":"MW",
    "gn:dem":440,
    "gn:feature_class":"P",
    "gn:feature_code":"PPL",
    "gn:name":"Cassapa",
    "gn:population":0,
    "gn:timezone":"Africa/Blantyre",
    "iso:country":"MW",
    "wof:name":"Cassapa",
    "wof:placetype":"locality"
},
  "geometry": {"coordinates":[34.61667,-15.63333],"type":"Point"}
}