{
  "type": "Feature",
  "properties": {
    "gn:admin1_code":"N",
    "gn:admin2_code":"15.0",
    "gn:asciiname":"Simon Moyo",
    "gn:country_code":"MW",
    "gn:dem":1142,
    "gn:feature_class":"P",
    "gn:feature_code":"PPL",
    "gn:name":"Simon Moyo",
    "gn:population":0,
    "gn:timezone":"Africa/Blantyre",
    "iso:country":"MW",
    "wof:name":"Simon Moyo",
    "wof:placetype":"locality"
},
  "geometry": {"coordinates":[33.33133,-11.56847],"type":"Point"}
}