{
  "type": "Feature",
  "properties": {
    "gn:admin1_code":"C",
    "gn:admin2_code":"6.0",
    "gn:asciiname":"Kalumbi",
    "gn:country_code":"MW",
    "gn:dem":1190,
    "gn:feature_class":"P",
    "gn:feature_code":"PPL",
    "gn:name":"Kalumbi",
    "gn:population":0,
    "gn:timezone":"Africa/Blantyre",
    "iso:country":"MW",
    "wof:name":"Kalumbi",
    "wof:placetype":"locality"
},
  "geometry": {"coordinates":[33.95,-14.25],"type":"Point"}
}