{
  "type": "Feature",
  "properties": {
    "gn:admin1_code":"C",
    "gn:admin2_code":"22.0",
    "gn:asciiname":"Chiunjiza",
    "gn:country_code":"MW",
    "gn:dem":512,
    "gn:feature_class":"P",
    "gn:feature_code":"PPL",
    "gn:name":"Chiunjiza",
    "gn:population":0,
    "gn:timezone":"Africa/Blantyre",
    "iso:country":"MW",
    "wof:name":"Chiunjiza",
    "wof:placetype":"locality"
},
  "geometry": {"coordinates":[34.29783,-13.49741],"type":"Point"}
}