{
  "type": "Feature",
  "properties": {
    "gn:admin1_code":"N",
    "gn:admin2_code":"15.0",
    "gn:asciiname":"Kabiri",
    "gn:country_code":"MW",
    "gn:dem":1274,
    "gn:feature_class":"P",
    "gn:feature_code":"PPL",
    "gn:name":"Kabiri",
    "gn:population":0,
    "gn:timezone":"Africa/Blantyre",
    "iso:country":"MW",
    "name:heb_x_preferred":[
        "\u05db\u05d1\u05d9\u05e8\u05d9"
    ],
    "name:por_x_preferred":[
        "Kabiri"
    ],
    "wof:name":"Kabiri",
    "wof:placetype":"locality"
},
  "geometry": {"coordinates":[33.78815,-12.47238],"type":"Point"}
}