{
  "type": "Feature",
  "properties": {
    "gn:admin1_code":"S",
    "gn:admin2_code":"2.0",
    "gn:asciiname":"Mikolongo",
    "gn:country_code":"MW",
    "gn:dem":204,
    "gn:feature_class":"P",
    "gn:feature_code":"PPL",
    "gn:name":"Mikolongo",
    "gn:population":0,
    "gn:timezone":"Africa/Blantyre",
    "iso:country":"MW",
    "name:und_x_variant":[
        "Mikorongo",
        "Mikolongo"
    ],
    "wof:name":"Mikolongo",
    "wof:placetype":"locality"
},
  "geometry": {"coordinates":[34.4831,-15.99843],"type":"Point"}
}