{
  "type": "Feature",
  "properties": {
    "gn:admin1_code":"C",
    "gn:admin2_code":"11.0",
    "gn:asciiname":"Mwanda",
    "gn:country_code":"MW",
    "gn:dem":1081,
    "gn:feature_class":"P",
    "gn:feature_code":"PPL",
    "gn:name":"Mwanda",
    "gn:population":0,
    "gn:timezone":"Africa/Blantyre",
    "iso:country":"MW",
    "name:urd_x_preferred":[
        "\u0645\u0648\u0627\u0646\u0688\u0627"
    ],
    "wof:name":"Mwanda",
    "wof:placetype":"locality"
},
  "geometry": {"coordinates":[33.42588,-13.58085],"type":"Point"}
}