{
  "type": "Feature",
  "properties": {
    "gn:admin1_code":"C",
    "gn:admin2_code":"13.0",
    "gn:asciiname":"Lombwa",
    "gn:country_code":"MW",
    "gn:dem":1076,
    "gn:feature_class":"P",
    "gn:feature_code":"PPL",
    "gn:name":"Lombwa",
    "gn:population":0,
    "gn:timezone":"Africa/Blantyre",
    "iso:country":"MW",
    "wof:name":"Lombwa",
    "wof:placetype":"locality"
},
  "geometry": {"coordinates":[33.06099,-13.47323],"type":"Point"}
}