{
  "type": "Feature",
  "properties": {
    "gn:admin1_code":"N",
    "gn:admin2_code":"15.0",
    "gn:asciiname":"Katolola Mfuni",
    "gn:country_code":"MW",
    "gn:dem":1141,
    "gn:feature_class":"P",
    "gn:feature_code":"PPL",
    "gn:name":"Katolola Mfuni",
    "gn:population":0,
    "gn:timezone":"Africa/Blantyre",
    "iso:country":"MW",
    "name:eng_x_preferred":[
        "Katolola Mfuni"
    ],
    "name:und_x_variant":[
        "Katorora Mfwuni"
    ],
    "wof:name":"Katolola Mfuni",
    "wof:placetype":"locality"
},
  "geometry": {"coordinates":[33.35295,-11.67801],"type":"Point"}
}