{
  "type": "Feature",
  "properties": {
    "gn:admin1_code":"C",
    "gn:admin2_code":"6.0",
    "gn:asciiname":"Chitengo",
    "gn:country_code":"MW",
    "gn:dem":1195,
    "gn:feature_class":"P",
    "gn:feature_code":"PPL",
    "gn:name":"Chitengo",
    "gn:population":0,
    "gn:timezone":"Africa/Blantyre",
    "iso:country":"MW",
    "wof:name":"Chitengo",
    "wof:placetype":"locality"
},
  "geometry": {"coordinates":[33.78333,-14.36667],"type":"Point"}
}