{
  "type": "Feature",
  "properties": {
    "gn:admin1_code":"S",
    "gn:admin2_code":"19.0",
    "gn:asciiname":"Monyo",
    "gn:country_code":"MW",
    "gn:dem":37,
    "gn:feature_class":"P",
    "gn:feature_code":"PPL",
    "gn:name":"Monyo",
    "gn:population":0,
    "gn:timezone":"Africa/Blantyre",
    "iso:country":"MW",
    "wof:name":"Monyo",
    "wof:placetype":"locality"
},
  "geometry": {"coordinates":[35.29574,-17.06082],"type":"Point"}
}