{
  "type": "Feature",
  "properties": {
    "gn:admin1_code":"S",
    "gn:admin2_code":"23.0",
    "gn:asciiname":"Pambiche",
    "gn:country_code":"MW",
    "gn:dem":631,
    "gn:feature_class":"P",
    "gn:feature_code":"PPL",
    "gn:name":"Pambiche",
    "gn:population":0,
    "gn:timezone":"Africa/Blantyre",
    "iso:country":"MW",
    "name:und_x_variant":[
        "Pambichi",
        "Pambiche"
    ],
    "wof:name":"Pambiche",
    "wof:placetype":"locality"
},
  "geometry": {"coordinates":[35.81149,-15.26484],"type":"Point"}
}