{
  "type": "Feature",
  "properties": {
    "gn:admin1_code":"C",
    "gn:admin2_code":"11.0",
    "gn:asciiname":"Santhe",
    "gn:country_code":"MW",
    "gn:dem":1206,
    "gn:feature_class":"P",
    "gn:feature_code":"PPL",
    "gn:name":"Santhe",
    "gn:population":0,
    "gn:timezone":"Africa/Blantyre",
    "iso:country":"MW",
    "wof:name":"Santhe",
    "wof:placetype":"locality"
},
  "geometry": {"coordinates":[33.43069000000001,-13.93082],"type":"Point"}
}