{
  "type": "Feature",
  "properties": {
    "gn:admin1_code":"C",
    "gn:admin2_code":"9.0",
    "gn:asciiname":"Ciwawalo",
    "gn:country_code":"MW",
    "gn:dem":1398,
    "gn:feature_class":"P",
    "gn:feature_code":"PPL",
    "gn:name":"Ciwawalo",
    "gn:population":0,
    "gn:timezone":"Africa/Blantyre",
    "iso:country":"MW",
    "wof:name":"Ciwawalo",
    "wof:placetype":"locality"
},
  "geometry": {"coordinates":[33.51880999999999,-12.39429],"type":"Point"}
}