{
  "type": "Feature",
  "properties": {
    "gn:admin1_code":"S",
    "gn:admin2_code":"30.0",
    "gn:asciiname":"Nkulambe",
    "gn:country_code":"MW",
    "gn:dem":727,
    "gn:feature_class":"P",
    "gn:feature_code":"PPL",
    "gn:name":"Nkulambe",
    "gn:population":0,
    "gn:timezone":"Africa/Blantyre",
    "iso:country":"MW",
    "wof:name":"Nkulambe",
    "wof:placetype":"locality"
},
  "geometry": {"coordinates":[35.75075,-15.85919],"type":"Point"}
}