{
  "type": "Feature",
  "properties": {
    "gn:admin1_code":"C",
    "gn:admin2_code":"9.0",
    "gn:asciiname":"Thosi",
    "gn:country_code":"MW",
    "gn:dem":1121,
    "gn:feature_class":"P",
    "gn:feature_code":"PPL",
    "gn:name":"Thosi",
    "gn:population":0,
    "gn:timezone":"Africa/Blantyre",
    "iso:country":"MW",
    "wof:name":"Thosi",
    "wof:placetype":"locality"
},
  "geometry": {"coordinates":[33.56667,-12.73333],"type":"Point"}
}