{
  "type": "Feature",
  "properties": {
    "gn:admin1_code":"N",
    "gn:admin2_code":"15.0",
    "gn:asciiname":"Chisau Mkandawire",
    "gn:country_code":"MW",
    "gn:dem":1090,
    "gn:feature_class":"P",
    "gn:feature_code":"PPL",
    "gn:name":"Chisau Mkandawire",
    "gn:population":0,
    "gn:timezone":"Africa/Blantyre",
    "iso:country":"MW",
    "wof:name":"Chisau Mkandawire",
    "wof:placetype":"locality"
},
  "geometry": {"coordinates":[33.50683,-11.17128],"type":"Point"}
}