{
  "type": "Feature",
  "properties": {
    "gn:admin1_code":"C",
    "gn:admin2_code":"18.0",
    "gn:asciiname":"Tenje",
    "gn:country_code":"MW",
    "gn:dem":752,
    "gn:feature_class":"P",
    "gn:feature_code":"PPL",
    "gn:name":"Tenje",
    "gn:population":0,
    "gn:timezone":"Africa/Blantyre",
    "iso:country":"MW",
    "wof:name":"Tenje",
    "wof:placetype":"locality"
},
  "geometry": {"coordinates":[34.03333,-12.91667],"type":"Point"}
}