{
  "type": "Feature",
  "properties": {
    "gn:admin1_code":"N",
    "gn:admin2_code":"15.0",
    "gn:asciiname":"Saulos",
    "gn:country_code":"MW",
    "gn:dem":1298,
    "gn:feature_class":"P",
    "gn:feature_code":"PPL",
    "gn:name":"Saulos",
    "gn:population":0,
    "gn:timezone":"Africa/Blantyre",
    "iso:country":"MW",
    "wof:name":"Saulos",
    "wof:placetype":"locality"
},
  "geometry": {"coordinates":[33.83213,-11.41145],"type":"Point"}
}