{
  "type": "Feature",
  "properties": {
    "gn:admin1_code":"C",
    "gn:admin2_code":"20.0",
    "gn:asciiname":"Chikwakwa",
    "gn:country_code":"MW",
    "gn:dem":1441,
    "gn:feature_class":"P",
    "gn:feature_code":"PPL",
    "gn:name":"Chikwakwa",
    "gn:population":0,
    "gn:timezone":"Africa/Blantyre",
    "iso:country":"MW",
    "wof:name":"Chikwakwa",
    "wof:placetype":"locality"
},
  "geometry": {"coordinates":[33.93333,-13.36667],"type":"Point"}
}