{
  "type": "Feature",
  "properties": {
    "gn:admin1_code":"N",
    "gn:admin2_code":"15.0",
    "gn:asciiname":"Chikomeni Thore",
    "gn:country_code":"MW",
    "gn:dem":1401,
    "gn:feature_class":"P",
    "gn:feature_code":"PPL",
    "gn:name":"Chikomeni Thore",
    "gn:population":0,
    "gn:timezone":"Africa/Blantyre",
    "iso:country":"MW",
    "wof:name":"Chikomeni Thore",
    "wof:placetype":"locality"
},
  "geometry": {"coordinates":[33.54738,-12.0631],"type":"Point"}
}