{
  "type": "Feature",
  "properties": {
    "gn:admin1_code":"C",
    "gn:admin2_code":"22.0",
    "gn:asciiname":"Msuta",
    "gn:country_code":"MW",
    "gn:dem":523,
    "gn:feature_class":"P",
    "gn:feature_code":"PPL",
    "gn:name":"Msuta",
    "gn:population":0,
    "gn:timezone":"Africa/Blantyre",
    "iso:country":"MW",
    "wof:name":"Msuta",
    "wof:placetype":"locality"
},
  "geometry": {"coordinates":[34.41667,-13.76667],"type":"Point"}
}