{
  "type": "Feature",
  "properties": {
    "gn:admin1_code":"C",
    "gn:admin2_code":"22.0",
    "gn:asciiname":"Karonga",
    "gn:country_code":"MW",
    "gn:dem":507,
    "gn:feature_class":"P",
    "gn:feature_code":"PPL",
    "gn:name":"Karonga",
    "gn:population":0,
    "gn:timezone":"Africa/Blantyre",
    "iso:country":"MW",
    "name:rus_x_preferred":[
        "\u041a\u0430\u0440\u043e\u043d\u0433\u0430"
    ],
    "name:und_x_variant":[
        "Karonsa",
        "Karonga"
    ],
    "wof:name":"Karonga",
    "wof:placetype":"locality"
},
  "geometry": {"coordinates":[34.44049,-13.77069],"type":"Point"}
}