{
  "type": "Feature",
  "properties": {
    "gn:admin1_code":"C",
    "gn:admin2_code":"22.0",
    "gn:asciiname":"Karonga",
    "gn:country_code":"MW",
    "gn:dem":507,
    "gn:feature_class":"P",
    "gn:feature_code":"PPL",
    "gn:name":"Karonga",
    "gn:population":0,
    "gn:timezone":"Africa/Blantyre",
    "iso:country":"MW",
    "name:azb_x_preferred":[
        "\u06a9\u0627\u0631\u0648\u0646\u0642\u0627"
    ],
    "name:bul_x_preferred":[
        "\u041a\u0430\u0440\u043e\u043d\u0433\u0430"
    ],
    "name:ceb_x_preferred":[
        "Karonga"
    ],
    "name:dan_x_preferred":[
        "Karonga"
    ],
    "name:deu_x_preferred":[
        "Karonga"
    ],
    "name:fas_x_preferred":[
        "\u06a9\u0627\u0631\u0648\u0646\u06af\u0627"
    ],
    "name:fra_x_preferred":[
        "Karonga"
    ],
    "name:ita_x_preferred":[
        "Karonga"
    ],
    "name:kor_x_preferred":[
        "\uce74\ub871\uac00"
    ],
    "name:lit_x_preferred":[
        "Karonga"
    ],
    "name:nld_x_preferred":[
        "Karonga"
    ],
    "name:nya_x_preferred":[
        "Karonga"
    ],
    "name:pol_x_preferred":[
        "Karonga"
    ],
    "name:ron_x_preferred":[
        "Karonga"
    ],
    "name:rus_x_preferred":[
        "\u041a\u0430\u0440\u043e\u043d\u0433\u0430"
    ],
    "name:swe_x_preferred":[
        "Karonga"
    ],
    "name:tum_x_preferred":[
        "Karonga"
    ],
    "name:tur_x_preferred":[
        "Karonga"
    ],
    "name:ukr_x_preferred":[
        "\u041a\u0430\u0440\u043e\u043d\u0433\u0430"
    ],
    "name:und_x_variant":[
        "Karonsa",
        "Karonga"
    ],
    "name:zho_x_preferred":[
        "\u5361\u9f99\u52a0"
    ],
    "wof:name":"Karonga",
    "wof:placetype":"locality"
},
  "geometry": {"coordinates":[34.44049,-13.77069],"type":"Point"}
}