{
  "type": "Feature",
  "properties": {
    "gn:admin1_code":"S",
    "gn:admin2_code":"24.0",
    "gn:asciiname":"Bwanasompho",
    "gn:country_code":"MW",
    "gn:dem":600,
    "gn:feature_class":"P",
    "gn:feature_code":"PPL",
    "gn:name":"Bwanasompho",
    "gn:population":0,
    "gn:timezone":"Africa/Blantyre",
    "iso:country":"MW",
    "wof:name":"Bwanasompho",
    "wof:placetype":"locality"
},
  "geometry": {"coordinates":[34.91374,-15.79348],"type":"Point"}
}