{
  "type": "Feature",
  "properties": {
    "gn:admin1_code":"N",
    "gn:admin2_code":"15.0",
    "gn:asciiname":"Damba",
    "gn:country_code":"MW",
    "gn:dem":1521,
    "gn:feature_class":"P",
    "gn:feature_code":"PPL",
    "gn:name":"Damba",
    "gn:population":0,
    "gn:timezone":"Africa/Blantyre",
    "iso:country":"MW",
    "name:cat_x_preferred":[
        "Paretroplus damii"
    ],
    "name:ceb_x_preferred":[
        "Paretroplus damii"
    ],
    "name:eus_x_preferred":[
        "Paretroplus damii"
    ],
    "name:fas_x_preferred":[
        "\u062f\u0645\u0628\u0627"
    ],
    "name:nld_x_preferred":[
        "Paretroplus damii"
    ],
    "name:por_x_preferred":[
        "Paretroplus damii"
    ],
    "name:spa_x_preferred":[
        "Paretroplus damii"
    ],
    "name:swe_x_preferred":[
        "Paretroplus damii"
    ],
    "name:vie_x_preferred":[
        "Paretroplus damii"
    ],
    "name:war_x_preferred":[
        "Paretroplus damii"
    ],
    "name:zho_x_preferred":[
        "\u9054\u7c73\u6c0f\u526f\u71b1\u9bdb"
    ],
    "wof:name":"Damba",
    "wof:placetype":"locality"
},
  "geometry": {"coordinates":[33.75,-12.33333],"type":"Point"}
}