{
  "type": "Feature",
  "properties": {
    "gn:admin1_code":"C",
    "gn:admin2_code":"22.0",
    "gn:asciiname":"Mtimasonjo",
    "gn:country_code":"MW",
    "gn:dem":473,
    "gn:feature_class":"P",
    "gn:feature_code":"PPL",
    "gn:name":"Mtimasonjo",
    "gn:population":0,
    "gn:timezone":"Africa/Blantyre",
    "iso:country":"MW",
    "wof:name":"Mtimasonjo",
    "wof:placetype":"locality"
},
  "geometry": {"coordinates":[34.55560999999999,-13.6452],"type":"Point"}
}