{
  "type": "Feature",
  "properties": {
    "gn:admin1_code":"S",
    "gn:admin2_code":"2.0",
    "gn:asciiname":"Jombo",
    "gn:country_code":"MW",
    "gn:dem":78,
    "gn:feature_class":"P",
    "gn:feature_code":"PPL",
    "gn:name":"Jombo",
    "gn:population":0,
    "gn:timezone":"Africa/Blantyre",
    "iso:country":"MW",
    "wof:name":"Jombo",
    "wof:placetype":"locality"
},
  "geometry": {"coordinates":[34.86667,-16.31667],"type":"Point"}
}