{
  "type": "Feature",
  "properties": {
    "gn:admin1_code":"N",
    "gn:admin2_code":"21.0",
    "gn:asciiname":"Nkope",
    "gn:country_code":"MW",
    "gn:dem":663,
    "gn:feature_class":"P",
    "gn:feature_code":"PPL",
    "gn:name":"Nkope",
    "gn:population":0,
    "gn:timezone":"Africa/Blantyre",
    "iso:country":"MW",
    "wof:name":"Nkope",
    "wof:placetype":"locality"
},
  "geometry": {"coordinates":[34.21607,-10.9255],"type":"Point"}
}