{
  "type": "Feature",
  "properties": {
    "gn:admin1_code":"S",
    "gn:admin2_code":"28.0",
    "gn:asciiname":"Nyenje",
    "gn:country_code":"MW",
    "gn:dem":778,
    "gn:feature_class":"P",
    "gn:feature_code":"PPL",
    "gn:name":"Nyenje",
    "gn:population":0,
    "gn:timezone":"Africa/Blantyre",
    "iso:country":"MW",
    "wof:name":"Nyenje",
    "wof:placetype":"locality"
},
  "geometry": {"coordinates":[35.53572,-14.80305],"type":"Point"}
}