{
  "type": "Feature",
  "properties": {
    "gn:admin1_code":"S",
    "gn:admin2_code":"24.0",
    "gn:asciiname":"Bangwe",
    "gn:country_code":"MW",
    "gn:dem":1509,
    "gn:feature_class":"P",
    "gn:feature_code":"PPL",
    "gn:name":"Bangwe",
    "gn:population":0,
    "gn:timezone":"Africa/Blantyre",
    "iso:country":"MW",
    "wof:name":"Bangwe",
    "wof:placetype":"locality"
},
  "geometry": {"coordinates":[35.10059,-15.82263],"type":"Point"}
}