{
  "type": "Feature",
  "properties": {
    "gn:admin1_code":"S",
    "gn:admin2_code":"19.0",
    "gn:asciiname":"Nyamula",
    "gn:country_code":"MW",
    "gn:dem":51,
    "gn:feature_class":"P",
    "gn:feature_code":"PPL",
    "gn:name":"Nyamula",
    "gn:population":0,
    "gn:timezone":"Africa/Blantyre",
    "iso:country":"MW",
    "wof:name":"Nyamula",
    "wof:placetype":"locality"
},
  "geometry": {"coordinates":[35.2777,-16.79356],"type":"Point"}
}