{
  "type": "Feature",
  "properties": {
    "gn:admin1_code":"S",
    "gn:admin2_code":"28.0",
    "gn:asciiname":"Mkwepele",
    "gn:country_code":"MW",
    "gn:dem":743,
    "gn:feature_class":"P",
    "gn:feature_code":"PPL",
    "gn:name":"Mkwepele",
    "gn:population":0,
    "gn:timezone":"Africa/Blantyre",
    "iso:country":"MW",
    "name:und_x_variant":[
        "Nkwepene",
        "Mkwepele"
    ],
    "wof:name":"Mkwepele",
    "wof:placetype":"locality"
},
  "geometry": {"coordinates":[35.64882,-14.58879],"type":"Point"}
}