{
  "type": "Feature",
  "properties": {
    "gn:admin1_code":"C",
    "gn:admin2_code":"13.0",
    "gn:asciiname":"Kalulu",
    "gn:country_code":"MW",
    "gn:dem":1068,
    "gn:feature_class":"P",
    "gn:feature_code":"PPL",
    "gn:name":"Kalulu",
    "gn:population":0,
    "gn:timezone":"Africa/Blantyre",
    "iso:country":"MW",
    "name:deu_x_preferred":[
        "Kalulu"
    ],
    "name:fin_x_preferred":[
        "Kalulu"
    ],
    "name:kor_x_preferred":[
        "\uce74\ub8e8\ub8e8"
    ],
    "name:rus_x_preferred":[
        "\u041a\u0430\u043b\u0443\u043b\u0443"
    ],
    "name:swe_x_preferred":[
        "Kalulu"
    ],
    "name:yor_x_preferred":[
        "Kalulu"
    ],
    "wof:name":"Kalulu",
    "wof:placetype":"locality"
},
  "geometry": {"coordinates":[33.02108,-13.57962],"type":"Point"}
}