{
  "type": "Feature",
  "properties": {
    "gn:admin1_code":"S",
    "gn:admin2_code":"30.0",
    "gn:asciiname":"Namilima",
    "gn:country_code":"MW",
    "gn:dem":674,
    "gn:feature_class":"P",
    "gn:feature_code":"PPL",
    "gn:name":"Namilima",
    "gn:population":0,
    "gn:timezone":"Africa/Blantyre",
    "iso:country":"MW",
    "wof:name":"Namilima",
    "wof:placetype":"locality"
},
  "geometry": {"coordinates":[35.8126,-15.71725],"type":"Point"}
}