{
  "type": "Feature",
  "properties": {
    "gn:admin1_code":"N",
    "gn:admin2_code":"15.0",
    "gn:asciiname":"Zebediya Makwakwa",
    "gn:country_code":"MW",
    "gn:dem":1178,
    "gn:feature_class":"P",
    "gn:feature_code":"PPL",
    "gn:name":"Zebediya Makwakwa",
    "gn:population":0,
    "gn:timezone":"Africa/Blantyre",
    "iso:country":"MW",
    "wof:name":"Zebediya Makwakwa",
    "wof:placetype":"locality"
},
  "geometry": {"coordinates":[33.70763,-11.21245],"type":"Point"}
}