{
  "type": "Feature",
  "properties": {
    "gn:admin1_code":"C",
    "gn:admin2_code":"9.0",
    "gn:asciiname":"Loni",
    "gn:country_code":"MW",
    "gn:dem":1155,
    "gn:feature_class":"P",
    "gn:feature_code":"PPL",
    "gn:name":"Loni",
    "gn:population":0,
    "gn:timezone":"Africa/Blantyre",
    "iso:country":"MW",
    "name:bih_x_preferred":[
        "\u0932\u094b\u0928\u0940"
    ],
    "name:gom_x_preferred":[
        "\u0932\u094b\u0923\u0940"
    ],
    "name:pus_x_preferred":[
        "\u0644\u0648\u0646\u064a"
    ],
    "wof:name":"Loni",
    "wof:placetype":"locality"
},
  "geometry": {"coordinates":[33.31667,-12.68333],"type":"Point"}
}