{
  "type": "Feature",
  "properties": {
    "gn:admin1_code":"C",
    "gn:admin2_code":"9.0",
    "gn:asciiname":"Mayani",
    "gn:country_code":"MW",
    "gn:dem":1084,
    "gn:feature_class":"P",
    "gn:feature_code":"PPL",
    "gn:name":"Mayani",
    "gn:population":0,
    "gn:timezone":"Africa/Blantyre",
    "iso:country":"MW",
    "wof:name":"Mayani",
    "wof:placetype":"locality"
},
  "geometry": {"coordinates":[33.45,-13.08333],"type":"Point"}
}