{
  "type": "Feature",
  "properties": {
    "gn:admin1_code":"C",
    "gn:admin2_code":"6.0",
    "gn:asciiname":"Kankomba",
    "gn:country_code":"MW",
    "gn:dem":1548,
    "gn:feature_class":"P",
    "gn:feature_code":"PPL",
    "gn:name":"Kankomba",
    "gn:population":0,
    "gn:timezone":"Africa/Blantyre",
    "iso:country":"MW",
    "name:und_x_variant":[
        "Kankoma",
        "Kankomba"
    ],
    "wof:name":"Kankomba",
    "wof:placetype":"locality"
},
  "geometry": {"coordinates":[34.26615,-14.23892],"type":"Point"}
}