{
  "type": "Feature",
  "properties": {
    "gn:admin1_code":"C",
    "gn:admin2_code":"11.0",
    "gn:asciiname":"Chilinde",
    "gn:country_code":"MW",
    "gn:dem":1100,
    "gn:feature_class":"P",
    "gn:feature_code":"PPL",
    "gn:name":"Chilinde",
    "gn:population":0,
    "gn:timezone":"Africa/Blantyre",
    "iso:country":"MW",
    "wof:name":"Chilinde",
    "wof:placetype":"locality"
},
  "geometry": {"coordinates":[33.81042,-13.99463],"type":"Point"}
}