{
  "type": "Feature",
  "properties": {
    "gn:admin1_code":"S",
    "gn:admin2_code":"23.0",
    "gn:asciiname":"Mkusagombe",
    "gn:country_code":"MW",
    "gn:dem":708,
    "gn:feature_class":"P",
    "gn:feature_code":"PPL",
    "gn:name":"Mkusagombe",
    "gn:population":0,
    "gn:timezone":"Africa/Blantyre",
    "iso:country":"MW",
    "wof:name":"Mkusagombe",
    "wof:placetype":"locality"
},
  "geometry": {"coordinates":[35.43333,-15.26667],"type":"Point"}
}