{
  "type": "Feature",
  "properties": {
    "gn:admin1_code":"C",
    "gn:admin2_code":"16.0",
    "gn:asciiname":"Chipusile",
    "gn:country_code":"MW",
    "gn:dem":1469,
    "gn:feature_class":"P",
    "gn:feature_code":"PPL",
    "gn:name":"Chipusile",
    "gn:population":0,
    "gn:timezone":"Africa/Blantyre",
    "iso:country":"MW",
    "wof:name":"Chipusile",
    "wof:placetype":"locality"
},
  "geometry": {"coordinates":[34.5837,-14.8064],"type":"Point"}
}