{
  "type": "Feature",
  "properties": {
    "gn:admin1_code":"N",
    "gn:admin2_code":"27.0",
    "gn:asciiname":"Dooko",
    "gn:country_code":"MW",
    "gn:dem":476,
    "gn:feature_class":"P",
    "gn:feature_code":"PPL",
    "gn:name":"Dooko",
    "gn:population":0,
    "gn:timezone":"Africa/Blantyre",
    "iso:country":"MW",
    "wof:name":"Dooko",
    "wof:placetype":"locality"
},
  "geometry": {"coordinates":[34.61667,-12.01667],"type":"Point"}
}