{
  "type": "Feature",
  "properties": {
    "gn:admin1_code":"S",
    "gn:admin2_code":"29.0",
    "gn:asciiname":"Chombe",
    "gn:country_code":"MW",
    "gn:dem":714,
    "gn:feature_class":"P",
    "gn:feature_code":"PPL",
    "gn:name":"Chombe",
    "gn:population":0,
    "gn:timezone":"Africa/Blantyre",
    "iso:country":"MW",
    "wof:name":"Chombe",
    "wof:placetype":"locality"
},
  "geometry": {"coordinates":[35.53074,-15.83717],"type":"Point"}
}