{
  "type": "Feature",
  "properties": {
    "gn:admin1_code":"S",
    "gn:admin2_code":"28.0",
    "gn:asciiname":"Nyandule",
    "gn:country_code":"MW",
    "gn:dem":661,
    "gn:feature_class":"P",
    "gn:feature_code":"PPL",
    "gn:name":"Nyandule",
    "gn:population":0,
    "gn:timezone":"Africa/Blantyre",
    "iso:country":"MW",
    "wof:name":"Nyandule",
    "wof:placetype":"locality"
},
  "geometry": {"coordinates":[35.78767,-14.7465],"type":"Point"}
}