{
  "type": "Feature",
  "properties": {
    "gn:admin1_code":"S",
    "gn:admin2_code":"23.0",
    "gn:asciiname":"Malika",
    "gn:country_code":"MW",
    "gn:dem":747,
    "gn:feature_class":"P",
    "gn:feature_code":"PPL",
    "gn:name":"Malika",
    "gn:population":0,
    "gn:timezone":"Africa/Blantyre",
    "iso:country":"MW",
    "name:ceb_x_preferred":[
        "Malika"
    ],
    "name:deu_x_preferred":[
        "Malika"
    ],
    "name:fra_x_preferred":[
        "Malika"
    ],
    "name:nep_x_preferred":[
        "\u092e\u093e\u0932\u093f\u0915\u093e"
    ],
    "name:pol_x_preferred":[
        "Malika"
    ],
    "wof:name":"Malika",
    "wof:placetype":"locality"
},
  "geometry": {"coordinates":[35.41667,-15.28333],"type":"Point"}
}