{
  "type": "Feature",
  "properties": {
    "gn:admin1_code":"C",
    "gn:admin2_code":"11.0",
    "gn:asciiname":"Mitundu",
    "gn:country_code":"MW",
    "gn:dem":1207,
    "gn:feature_class":"P",
    "gn:feature_code":"PPL",
    "gn:name":"Mitundu",
    "gn:population":0,
    "gn:timezone":"Africa/Blantyre",
    "iso:country":"MW",
    "name:und_x_variant":[
        "Mtundu",
        "Mitundu"
    ],
    "wof:name":"Mitundu",
    "wof:placetype":"locality"
},
  "geometry": {"coordinates":[33.77885,-14.24695],"type":"Point"}
}