{
  "type": "Feature",
  "properties": {
    "gn:admin1_code":"S",
    "gn:admin2_code":"28.0",
    "gn:asciiname":"Chipanda",
    "gn:country_code":"MW",
    "gn:dem":483,
    "gn:feature_class":"P",
    "gn:feature_code":"PPL",
    "gn:name":"Chipanda",
    "gn:population":0,
    "gn:timezone":"Africa/Blantyre",
    "iso:country":"MW",
    "wof:name":"Chipanda",
    "wof:placetype":"locality"
},
  "geometry": {"coordinates":[35.31667,-14.88333],"type":"Point"}
}