{
  "type": "Feature",
  "properties": {
    "gn:admin1_code":"N",
    "gn:admin2_code":"15.0",
    "gn:asciiname":"Nyungwe Mphaka",
    "gn:country_code":"MW",
    "gn:dem":1168,
    "gn:feature_class":"P",
    "gn:feature_code":"PPL",
    "gn:name":"Nyungwe Mphaka",
    "gn:population":0,
    "gn:timezone":"Africa/Blantyre",
    "iso:country":"MW",
    "wof:name":"Nyungwe Mphaka",
    "wof:placetype":"locality"
},
  "geometry": {"coordinates":[33.37044,-11.78361],"type":"Point"}
}