{
  "type": "Feature",
  "properties": {
    "gn:admin1_code":"S",
    "gn:admin2_code":"24.0",
    "gn:asciiname":"Kausiwa",
    "gn:country_code":"MW",
    "gn:dem":820,
    "gn:feature_class":"P",
    "gn:feature_code":"PPL",
    "gn:name":"Kausiwa",
    "gn:population":0,
    "gn:timezone":"Africa/Blantyre",
    "iso:country":"MW",
    "wof:name":"Kausiwa",
    "wof:placetype":"locality"
},
  "geometry": {"coordinates":[34.94391,-15.80125],"type":"Point"}
}