{
  "type": "Feature",
  "properties": {
    "gn:admin1_code":"C",
    "gn:admin2_code":"13.0",
    "gn:asciiname":"Kalambani",
    "gn:country_code":"MW",
    "gn:dem":1118,
    "gn:feature_class":"P",
    "gn:feature_code":"PPL",
    "gn:name":"Kalambani",
    "gn:population":0,
    "gn:timezone":"Africa/Blantyre",
    "iso:country":"MW",
    "wof:name":"Kalambani",
    "wof:placetype":"locality"
},
  "geometry": {"coordinates":[33.01795,-13.80113],"type":"Point"}
}