{
  "type": "Feature",
  "properties": {
    "gn:admin1_code":"N",
    "gn:admin2_code":"17.0",
    "gn:asciiname":"Kanyole",
    "gn:country_code":"MW",
    "gn:dem":545,
    "gn:feature_class":"P",
    "gn:feature_code":"PPL",
    "gn:name":"Kanyole",
    "gn:population":0,
    "gn:timezone":"Africa/Blantyre",
    "iso:country":"MW",
    "wof:name":"Kanyole",
    "wof:placetype":"locality"
},
  "geometry": {"coordinates":[34.31667,-11.66667],"type":"Point"}
}