{
  "type": "Feature",
  "properties": {
    "gn:admin1_code":"S",
    "gn:admin2_code":"28.0",
    "gn:asciiname":"Dinje",
    "gn:country_code":"MW",
    "gn:dem":641,
    "gn:feature_class":"P",
    "gn:feature_code":"PPL",
    "gn:name":"Dinje",
    "gn:population":0,
    "gn:timezone":"Africa/Blantyre",
    "iso:country":"MW",
    "wof:name":"Dinje",
    "wof:placetype":"locality"
},
  "geometry": {"coordinates":[35.85059000000001,-14.7346],"type":"Point"}
}