{
  "type": "Feature",
  "properties": {
    "gn:admin1_code":"C",
    "gn:admin2_code":"13.0",
    "gn:asciiname":"Nyoka",
    "gn:country_code":"MW",
    "gn:dem":1226,
    "gn:feature_class":"P",
    "gn:feature_code":"PPL",
    "gn:name":"Nyoka",
    "gn:population":0,
    "gn:timezone":"Africa/Blantyre",
    "iso:country":"MW",
    "wof:name":"Nyoka",
    "wof:placetype":"locality"
},
  "geometry": {"coordinates":[32.90562,-13.70037],"type":"Point"}
}