{
  "type": "Feature",
  "properties": {
    "gn:admin1_code":"C",
    "gn:admin2_code":"20.0",
    "gn:asciiname":"Ntambalero",
    "gn:country_code":"MW",
    "gn:dem":1074,
    "gn:feature_class":"P",
    "gn:feature_code":"PPL",
    "gn:name":"Ntambalero",
    "gn:population":0,
    "gn:timezone":"Africa/Blantyre",
    "iso:country":"MW",
    "wof:name":"Ntambalero",
    "wof:placetype":"locality"
},
  "geometry": {"coordinates":[34.05,-13.46667],"type":"Point"}
}