{
  "type": "Feature",
  "properties": {
    "gn:admin1_code":"C",
    "gn:admin2_code":"16.0",
    "gn:asciiname":"Chikadya",
    "gn:country_code":"MW",
    "gn:dem":613,
    "gn:feature_class":"P",
    "gn:feature_code":"PPL",
    "gn:name":"Chikadya",
    "gn:population":0,
    "gn:timezone":"Africa/Blantyre",
    "iso:country":"MW",
    "wof:name":"Chikadya",
    "wof:placetype":"locality"
},
  "geometry": {"coordinates":[34.80336,-14.64542],"type":"Point"}
}