{
  "type": "Feature",
  "properties": {
    "gn:admin1_code":"N",
    "gn:admin2_code":"21.0",
    "gn:asciiname":"Mwembe",
    "gn:country_code":"MW",
    "gn:dem":1299,
    "gn:feature_class":"P",
    "gn:feature_code":"PPL",
    "gn:name":"Mwembe",
    "gn:population":0,
    "gn:timezone":"Africa/Blantyre",
    "iso:country":"MW",
    "wof:name":"Mwembe",
    "wof:placetype":"locality"
},
  "geometry": {"coordinates":[34.09418,-10.59578],"type":"Point"}
}