{
  "type": "Feature",
  "properties": {
    "gn:admin1_code":"S",
    "gn:admin2_code":"12.0",
    "gn:asciiname":"Kwitanda",
    "gn:country_code":"MW",
    "gn:dem":534,
    "gn:feature_class":"P",
    "gn:feature_code":"PPL",
    "gn:name":"Kwitanda",
    "gn:population":0,
    "gn:timezone":"Africa/Blantyre",
    "iso:country":"MW",
    "wof:name":"Kwitanda",
    "wof:placetype":"locality"
},
  "geometry": {"coordinates":[35.37237000000001,-14.53041],"type":"Point"}
}