{
  "type": "Feature",
  "properties": {
    "gn:admin1_code":"C",
    "gn:admin2_code":"6.0",
    "gn:asciiname":"Pango",
    "gn:country_code":"MW",
    "gn:dem":1382,
    "gn:feature_class":"P",
    "gn:feature_code":"PPL",
    "gn:name":"Pango",
    "gn:population":0,
    "gn:timezone":"Africa/Blantyre",
    "iso:country":"MW",
    "name:ara_x_preferred":[
        "\u0628\u0627\u0646\u063a\u0648"
    ],
    "name:cat_x_preferred":[
        "Pango"
    ],
    "name:deu_x_preferred":[
        "Pango"
    ],
    "name:fas_x_preferred":[
        "\u067e\u0646\u06af\u0648"
    ],
    "name:fra_x_preferred":[
        "Pango"
    ],
    "name:heb_x_preferred":[
        "Pango"
    ],
    "name:hun_x_preferred":[
        "Pango"
    ],
    "name:jpn_x_preferred":[
        "Pango"
    ],
    "name:nld_x_preferred":[
        "Pango"
    ],
    "name:nor_x_preferred":[
        "Pango"
    ],
    "name:pol_x_preferred":[
        "Pango"
    ],
    "name:por_x_preferred":[
        "Pango"
    ],
    "name:rus_x_preferred":[
        "Pango"
    ],
    "name:sin_x_preferred":[
        "\u0db4\u0dd0\u0db1\u0dca\u0d9c\u0ddd"
    ],
    "name:spa_x_preferred":[
        "Pango"
    ],
    "name:tgl_x_preferred":[
        "Pango"
    ],
    "name:zho_x_preferred":[
        "Pango"
    ],
    "wof:name":"Pango",
    "wof:placetype":"locality"
},
  "geometry": {"coordinates":[34.31667,-14.16667],"type":"Point"}
}