{
  "type": "Feature",
  "properties": {
    "gn:admin1_code":"S",
    "gn:admin2_code":"12.0",
    "gn:asciiname":"Kukulanga",
    "gn:country_code":"MW",
    "gn:dem":489,
    "gn:feature_class":"P",
    "gn:feature_code":"PPL",
    "gn:name":"Kukulanga",
    "gn:population":0,
    "gn:timezone":"Africa/Blantyre",
    "iso:country":"MW",
    "name:und_x_variant":[
        "Kukalanjes Village",
        "Kukalanje",
        "Kukulanga"
    ],
    "wof:name":"Kukulanga",
    "wof:placetype":"locality"
},
  "geometry": {"coordinates":[35.18068,-14.63641],"type":"Point"}
}