{
  "type": "Feature",
  "properties": {
    "gn:admin1_code":"N",
    "gn:admin2_code":"4.0",
    "gn:asciiname":"Kenan Ngomba",
    "gn:country_code":"MW",
    "gn:dem":1324,
    "gn:feature_class":"P",
    "gn:feature_code":"PPL",
    "gn:name":"Kenan Ngomba",
    "gn:population":0,
    "gn:timezone":"Africa/Blantyre",
    "iso:country":"MW",
    "wof:name":"Kenan Ngomba",
    "wof:placetype":"locality"
},
  "geometry": {"coordinates":[33.68333,-10.08333],"type":"Point"}
}