{
  "type": "Feature",
  "properties": {
    "gn:admin1_code":"S",
    "gn:admin2_code":"24.0",
    "gn:asciiname":"Mandala",
    "gn:country_code":"MW",
    "gn:dem":1019,
    "gn:feature_class":"P",
    "gn:feature_code":"PPL",
    "gn:name":"Mandala",
    "gn:population":0,
    "gn:timezone":"Africa/Blantyre",
    "iso:country":"MW",
    "wof:name":"Mandala",
    "wof:placetype":"locality"
},
  "geometry": {"coordinates":[35.00592,-15.79369],"type":"Point"}
}