{
  "type": "Feature",
  "properties": {
    "gn:admin1_code":"S",
    "gn:admin2_code":"24.0",
    "gn:asciiname":"Mandala",
    "gn:country_code":"MW",
    "gn:dem":1019,
    "gn:feature_class":"P",
    "gn:feature_code":"PPL",
    "gn:name":"Mandala",
    "gn:population":0,
    "gn:timezone":"Africa/Blantyre",
    "iso:country":"MW",
    "name:ara_x_preferred":[
        "\u0645\u0627\u0646\u062f\u0627\u0644\u0627"
    ],
    "name:aze_x_preferred":[
        "Mandala"
    ],
    "name:bel_x_preferred":[
        "\u041c\u0430\u043d\u0434\u0430\u043b\u0430"
    ],
    "name:bod_x_preferred":[
        "\u0f51\u0f40\u0fb1\u0f72\u0f63\u0f0b\u0f60\u0f41\u0f7c\u0f62\u0f0d"
    ],
    "name:bul_x_preferred":[
        "\u041c\u0430\u043d\u0434\u0430\u043b\u0430"
    ],
    "name:cat_x_preferred":[
        "Mandala"
    ],
    "name:ces_x_preferred":[
        "Mandala"
    ],
    "name:cym_x_preferred":[
        "Mandala"
    ],
    "name:dan_x_preferred":[
        "Mandala"
    ],
    "name:deu_x_preferred":[
        "Mandala"
    ],
    "name:epo_x_preferred":[
        "Mandalo"
    ],
    "name:est_x_preferred":[
        "Mandala"
    ],
    "name:eus_x_preferred":[
        "Mandala"
    ],
    "name:fas_x_preferred":[
        "\u0645\u0627\u0646\u062f\u0627\u0644\u0627"
    ],
    "name:fin_x_preferred":[
        "Mandala"
    ],
    "name:fra_x_preferred":[
        "Mandala"
    ],
    "name:fry_x_preferred":[
        "Mandala"
    ],
    "name:heb_x_preferred":[
        "\u05de\u05e0\u05d3\u05dc\u05d4"
    ],
    "name:hin_x_preferred":[
        "\u092e\u0902\u0921\u0932"
    ],
    "name:hun_x_preferred":[
        "Mandala"
    ],
    "name:hye_x_preferred":[
        "\u0544\u0561\u0576\u0564\u0561\u056c\u0561"
    ],
    "name:ind_x_preferred":[
        "Mandala"
    ],
    "name:ita_x_preferred":[
        "Ma\u1e47\u1e0dala"
    ],
    "name:jav_x_preferred":[
        "Mandala"
    ],
    "name:jpn_x_preferred":[
        "\u66fc\u837c\u7f85"
    ],
    "name:kan_x_preferred":[
        "\u0cae\u0c82\u0ca1\u0cb2"
    ],
    "name:kat_x_preferred":[
        "\u10db\u10d0\u10dc\u10d3\u10d0\u10da\u10d0"
    ],
    "name:kor_x_preferred":[
        "\ub9cc\ub2e4\ub77c"
    ],
    "name:lav_x_preferred":[
        "Mandala"
    ],
    "name:lit_x_preferred":[
        "Mandala"
    ],
    "name:ltz_x_preferred":[
        "Mandala"
    ],
    "name:nld_x_preferred":[
        "Mandala"
    ],
    "name:nor_x_preferred":[
        "Mandala"
    ],
    "name:pol_x_preferred":[
        "Mandala"
    ],
    "name:por_x_preferred":[
        "Mandala"
    ],
    "name:ron_x_preferred":[
        "Mandala"
    ],
    "name:rus_x_preferred":[
        "\u041c\u0430\u043d\u0434\u0430\u043b\u0430"
    ],
    "name:slk_x_preferred":[
        "Mandala"
    ],
    "name:spa_x_preferred":[
        "Mandala"
    ],
    "name:srp_x_preferred":[
        "\u041c\u0430\u043d\u0434\u0430\u043b\u0430"
    ],
    "name:sun_x_preferred":[
        "Mandala"
    ],
    "name:swe_x_preferred":[
        "Mandala"
    ],
    "name:tha_x_preferred":[
        "\u0e21\u0e13\u0e11\u0e25"
    ],
    "name:tur_x_preferred":[
        "Mandala"
    ],
    "name:ukr_x_preferred":[
        "\u041c\u0430\u043d\u0434\u0430\u043b\u0430"
    ],
    "name:urd_x_preferred":[
        "\u0645\u0646\u0688\u0644"
    ],
    "name:vie_x_preferred":[
        "M\u1ea1n-\u0111\u00e0-la"
    ],
    "name:zho_x_preferred":[
        "\u66fc\u837c\u7f85"
    ],
    "wof:name":"Mandala",
    "wof:placetype":"locality"
},
  "geometry": {"coordinates":[35.00592,-15.79369],"type":"Point"}
}