{
  "type": "Feature",
  "properties": {
    "gn:admin1_code":"N",
    "gn:admin2_code":"17.0",
    "gn:asciiname":"Lonya",
    "gn:country_code":"MW",
    "gn:dem":605,
    "gn:feature_class":"P",
    "gn:feature_code":"PPL",
    "gn:name":"Lonya",
    "gn:population":0,
    "gn:timezone":"Africa/Blantyre",
    "iso:country":"MW",
    "wof:name":"Lonya",
    "wof:placetype":"locality"
},
  "geometry": {"coordinates":[34.30321,-11.65422],"type":"Point"}
}