{
  "type": "Feature",
  "properties": {
    "gn:admin1_code":"N",
    "gn:admin2_code":"17.0",
    "gn:asciiname":"Mbosa",
    "gn:country_code":"MW",
    "gn:dem":487,
    "gn:feature_class":"P",
    "gn:feature_code":"PPL",
    "gn:name":"Mbosa",
    "gn:population":0,
    "gn:timezone":"Africa/Blantyre",
    "iso:country":"MW",
    "wof:name":"Mbosa",
    "wof:placetype":"locality"
},
  "geometry": {"coordinates":[34.05535,-12.00971],"type":"Point"}
}