{
  "type": "Feature",
  "properties": {
    "gn:country":"MW",
    "gn:fcode":"ADM2",
    "gn:pop":382590,
    "iso:country":"MW",
    "label:eng_x_preferred_longname":[
        "Ntcheu District"
    ],
    "label:eng_x_preferred_placetype":[
        "district"
    ],
    "name:eng_x_preferred":[
        "Ntcheu"
    ],
    "name:eng_x_variant":[
        "Ntcheu District"
    ],
    "name:unk_x_variant":[
        "Ncheu District"
    ],
    "qs:name":"Ntcheu District",
    "qs:photos_9r":0,
    "qs:photos_sr":0,
    "qs:pop_sr":"10",
    "wd:wordcount":551,
    "wof:name":"Ntcheu",
    "wof:placetype":"county",
    "wof:placetype_local":"district",
    "wof:population":382590
},
  "geometry": {"coordinates":[34.75,-14.75],"type":"Point"}
}