{
  "type": "Feature",
  "properties": {
    "gn:admin1_code":"C",
    "gn:admin2_code":"13.0",
    "gn:asciiname":"Siwerera",
    "gn:country_code":"MW",
    "gn:dem":1113,
    "gn:feature_class":"P",
    "gn:feature_code":"PPL",
    "gn:name":"Siwerera",
    "gn:population":0,
    "gn:timezone":"Africa/Blantyre",
    "iso:country":"MW",
    "wof:name":"Siwerera",
    "wof:placetype":"locality"
},
  "geometry": {"coordinates":[33.08333,-13.83333],"type":"Point"}
}