{
  "type": "Feature",
  "properties": {
    "gn:admin1_code":"C",
    "gn:admin2_code":"13.0",
    "gn:asciiname":"Chisasa",
    "gn:country_code":"MW",
    "gn:dem":1061,
    "gn:feature_class":"P",
    "gn:feature_code":"PPL",
    "gn:name":"Chisasa",
    "gn:population":0,
    "gn:timezone":"Africa/Blantyre",
    "iso:country":"MW",
    "wof:name":"Chisasa",
    "wof:placetype":"locality"
},
  "geometry": {"coordinates":[33.13829,-13.40201],"type":"Point"}
}