{
  "type": "Feature",
  "properties": {
    "gn:admin1_code":"N",
    "gn:admin2_code":"17.0",
    "gn:asciiname":"Mankhambira",
    "gn:country_code":"MW",
    "gn:dem":482,
    "gn:feature_class":"P",
    "gn:feature_code":"PPL",
    "gn:name":"Mankhambira",
    "gn:population":0,
    "gn:timezone":"Africa/Blantyre",
    "iso:country":"MW",
    "wof:name":"Mankhambira",
    "wof:placetype":"locality"
},
  "geometry": {"coordinates":[34.29578,-11.72058],"type":"Point"}
}