{
  "type": "Feature",
  "properties": {
    "gn:admin1_code":"N",
    "gn:admin2_code":"8.0",
    "gn:asciiname":"Mwenitete",
    "gn:country_code":"MW",
    "gn:dem":491,
    "gn:feature_class":"P",
    "gn:feature_code":"PPL",
    "gn:name":"Mwenitete",
    "gn:population":0,
    "gn:timezone":"Africa/Blantyre",
    "iso:country":"MW",
    "wof:name":"Mwenitete",
    "wof:placetype":"locality"
},
  "geometry": {"coordinates":[33.87179,-9.8124],"type":"Point"}
}