{
  "type": "Feature",
  "properties": {
    "gn:admin1_code":"N",
    "gn:admin2_code":"15.0",
    "gn:asciiname":"Kazembe",
    "gn:country_code":"MW",
    "gn:dem":1030,
    "gn:feature_class":"P",
    "gn:feature_code":"PPL",
    "gn:name":"Kazembe",
    "gn:population":0,
    "gn:timezone":"Africa/Blantyre",
    "iso:country":"MW",
    "name:cat_x_preferred":[
        "Kazembe"
    ],
    "name:ind_x_preferred":[
        "Kerajaan Kazembe"
    ],
    "name:lit_x_preferred":[
        "Kazemb\u0117"
    ],
    "wof:name":"Kazembe",
    "wof:placetype":"locality"
},
  "geometry": {"coordinates":[33.70061,-12.64859],"type":"Point"}
}