{
  "type": "Feature",
  "properties": {
    "gn:admin1_code":"C",
    "gn:admin2_code":"9.0",
    "gn:asciiname":"Chipekwe",
    "gn:country_code":"MW",
    "gn:dem":1132,
    "gn:feature_class":"P",
    "gn:feature_code":"PPL",
    "gn:name":"Chipekwe",
    "gn:population":0,
    "gn:timezone":"Africa/Blantyre",
    "iso:country":"MW",
    "wof:name":"Chipekwe",
    "wof:placetype":"locality"
},
  "geometry": {"coordinates":[33.47662,-13.12594],"type":"Point"}
}