{
  "type": "Feature",
  "properties": {
    "gn:admin1_code":"S",
    "gn:admin2_code":"31.0",
    "gn:asciiname":"Kaingilira",
    "gn:country_code":"MW",
    "gn:dem":1108,
    "gn:feature_class":"P",
    "gn:feature_code":"PPL",
    "gn:name":"Kaingilira",
    "gn:population":0,
    "gn:timezone":"Africa/Blantyre",
    "iso:country":"MW",
    "wof:name":"Kaingilira",
    "wof:placetype":"locality"
},
  "geometry": {"coordinates":[34.54847,-15.37162],"type":"Point"}
}