{
  "type": "Feature",
  "properties": {
    "gn:admin1_code":"C",
    "gn:admin2_code":"16.0",
    "gn:asciiname":"Chiwiza",
    "gn:country_code":"MW",
    "gn:dem":676,
    "gn:feature_class":"P",
    "gn:feature_code":"PPL",
    "gn:name":"Chiwiza",
    "gn:population":0,
    "gn:timezone":"Africa/Blantyre",
    "iso:country":"MW",
    "wof:name":"Chiwiza",
    "wof:placetype":"locality"
},
  "geometry": {"coordinates":[34.84735,-14.65999],"type":"Point"}
}