{
  "type": "Feature",
  "properties": {
    "gn:admin1_code":"N",
    "gn:admin2_code":"21.0",
    "gn:asciiname":"N'gonga",
    "gn:country_code":"MW",
    "gn:dem":1051,
    "gn:feature_class":"P",
    "gn:feature_code":"PPL",
    "gn:name":"N\u2019gonga",
    "gn:population":0,
    "gn:timezone":"Africa/Blantyre",
    "iso:country":"MW",
    "wof:name":"N'gonga",
    "wof:placetype":"locality"
},
  "geometry": {"coordinates":[33.94357,-10.94478],"type":"Point"}
}