{
  "type": "Feature",
  "properties": {
    "gn:admin1_code":"C",
    "gn:admin2_code":"7.0",
    "gn:asciiname":"Jemus",
    "gn:country_code":"MW",
    "gn:dem":1240,
    "gn:feature_class":"P",
    "gn:feature_code":"PPL",
    "gn:name":"Jemus",
    "gn:population":0,
    "gn:timezone":"Africa/Blantyre",
    "iso:country":"MW",
    "wof:name":"Jemus",
    "wof:placetype":"locality"
},
  "geometry": {"coordinates":[34.00332,-13.64786],"type":"Point"}
}