{
  "type": "Feature",
  "properties": {
    "gn:admin1_code":"C",
    "gn:admin2_code":"6.0",
    "gn:asciiname":"Citundu",
    "gn:country_code":"MW",
    "gn:dem":1392,
    "gn:feature_class":"P",
    "gn:feature_code":"PPL",
    "gn:name":"Citundu",
    "gn:population":0,
    "gn:timezone":"Africa/Blantyre",
    "iso:country":"MW",
    "wof:name":"Citundu",
    "wof:placetype":"locality"
},
  "geometry": {"coordinates":[34.26225,-14.1018],"type":"Point"}
}