{
  "type": "Feature",
  "properties": {
    "gn:admin1_code":"S",
    "gn:admin2_code":"25.0",
    "gn:asciiname":"Chimelango",
    "gn:country_code":"MW",
    "gn:dem":855,
    "gn:feature_class":"P",
    "gn:feature_code":"PPL",
    "gn:name":"Chimelango",
    "gn:population":0,
    "gn:timezone":"Africa/Blantyre",
    "iso:country":"MW",
    "wof:name":"Chimelango",
    "wof:placetype":"locality"
},
  "geometry": {"coordinates":[34.43631,-15.65556],"type":"Point"}
}