{
  "type": "Feature",
  "properties": {
    "gn:admin1_code":"C",
    "gn:admin2_code":"9.0",
    "gn:asciiname":"Makhula",
    "gn:country_code":"MW",
    "gn:dem":1025,
    "gn:feature_class":"P",
    "gn:feature_code":"PPL",
    "gn:name":"Makhula",
    "gn:population":0,
    "gn:timezone":"Africa/Blantyre",
    "iso:country":"MW",
    "wof:name":"Makhula",
    "wof:placetype":"locality"
},
  "geometry": {"coordinates":[33.39143,-12.85893],"type":"Point"}
}