{
  "type": "Feature",
  "properties": {
    "gn:admin1_code":"N",
    "gn:admin2_code":"4.0",
    "gn:asciiname":"Mwenefumbo",
    "gn:country_code":"MW",
    "gn:dem":1150,
    "gn:feature_class":"P",
    "gn:feature_code":"PPL",
    "gn:name":"Mwenefumbo",
    "gn:population":0,
    "gn:timezone":"Africa/Blantyre",
    "iso:country":"MW",
    "name:eng_x_preferred":[
        "Mwenefumbo"
    ],
    "name:und_x_variant":[
        "Mwenefumba"
    ],
    "wof:name":"Mwenefumbo",
    "wof:placetype":"locality"
},
  "geometry": {"coordinates":[33.40713,-9.60103],"type":"Point"}
}