{
  "type": "Feature",
  "properties": {
    "gn:admin1_code":"S",
    "gn:admin2_code":"19.0",
    "gn:asciiname":"Mbenje",
    "gn:country_code":"MW",
    "gn:dem":165,
    "gn:feature_class":"P",
    "gn:feature_code":"PPL",
    "gn:name":"Mbenje",
    "gn:population":0,
    "gn:timezone":"Africa/Blantyre",
    "iso:country":"MW",
    "wof:name":"Mbenje",
    "wof:placetype":"locality"
},
  "geometry": {"coordinates":[35.18333,-16.98333],"type":"Point"}
}