{
  "type": "Feature",
  "properties": {
    "gn:admin1_code":"C",
    "gn:admin2_code":"7.0",
    "gn:asciiname":"Nomyimbe",
    "gn:country_code":"MW",
    "gn:dem":1166,
    "gn:feature_class":"P",
    "gn:feature_code":"PPL",
    "gn:name":"Nomyimbe",
    "gn:population":0,
    "gn:timezone":"Africa/Blantyre",
    "iso:country":"MW",
    "name:und_x_variant":[
        "Nomvimbe",
        "Nomyimbe"
    ],
    "wof:name":"Nomyimbe",
    "wof:placetype":"locality"
},
  "geometry": {"coordinates":[34.05206,-13.70026],"type":"Point"}
}