{
  "type": "Feature",
  "properties": {
    "gn:admin1_code":"C",
    "gn:admin2_code":"20.0",
    "gn:asciiname":"Kasakula Woyera",
    "gn:country_code":"MW",
    "gn:dem":740,
    "gn:feature_class":"P",
    "gn:feature_code":"PPL",
    "gn:name":"Kasakula Woyera",
    "gn:population":0,
    "gn:timezone":"Africa/Blantyre",
    "iso:country":"MW",
    "name:und_x_variant":[
        "Kasakula",
        "Kasakula Woyera"
    ],
    "wof:name":"Kasakula Woyera",
    "wof:placetype":"locality"
},
  "geometry": {"coordinates":[34.08333,-13.35],"type":"Point"}
}