{
  "type": "Feature",
  "properties": {
    "gn:admin1_code":"N",
    "gn:admin2_code":"8.0",
    "gn:asciiname":"Kasguli",
    "gn:country_code":"MW",
    "gn:dem":1140,
    "gn:feature_class":"P",
    "gn:feature_code":"PPL",
    "gn:name":"Kasguli",
    "gn:population":0,
    "gn:timezone":"Africa/Blantyre",
    "iso:country":"MW",
    "wof:name":"Kasguli",
    "wof:placetype":"locality"
},
  "geometry": {"coordinates":[33.81667,-10.18333],"type":"Point"}
}