{
  "type": "Feature",
  "properties": {
    "gn:admin1_code":"C",
    "gn:admin2_code":"6.0",
    "gn:asciiname":"Magunditsa",
    "gn:country_code":"MW",
    "gn:dem":1528,
    "gn:feature_class":"P",
    "gn:feature_code":"PPL",
    "gn:name":"Magunditsa",
    "gn:population":0,
    "gn:timezone":"Africa/Blantyre",
    "iso:country":"MW",
    "wof:name":"Magunditsa",
    "wof:placetype":"locality"
},
  "geometry": {"coordinates":[34.332,-14.269],"type":"Point"}
}