{
  "type": "Feature",
  "properties": {
    "gn:admin1_code":"S",
    "gn:admin2_code":"23.0",
    "gn:asciiname":"Nambesa",
    "gn:country_code":"MW",
    "gn:dem":786,
    "gn:feature_class":"P",
    "gn:feature_code":"PPL",
    "gn:name":"Nambesa",
    "gn:population":0,
    "gn:timezone":"Africa/Blantyre",
    "iso:country":"MW",
    "wof:name":"Nambesa",
    "wof:placetype":"locality"
},
  "geometry": {"coordinates":[35.38333,-15.41667],"type":"Point"}
}