{
  "type": "Feature",
  "properties": {
    "gn:admin1_code":"N",
    "gn:admin2_code":"8.0",
    "gn:asciiname":"Mwafulirwa",
    "gn:country_code":"MW",
    "gn:dem":551,
    "gn:feature_class":"P",
    "gn:feature_code":"PPL",
    "gn:name":"Mwafulirwa",
    "gn:population":0,
    "gn:timezone":"Africa/Blantyre",
    "iso:country":"MW",
    "wof:name":"Mwafulirwa",
    "wof:placetype":"locality"
},
  "geometry": {"coordinates":[34.18333,-10.41667],"type":"Point"}
}