{
  "type": "Feature",
  "properties": {
    "gn:admin1_code":"C",
    "gn:admin2_code":"16.0",
    "gn:asciiname":"Mphola",
    "gn:country_code":"MW",
    "gn:dem":626,
    "gn:feature_class":"P",
    "gn:feature_code":"PPL",
    "gn:name":"Mphola",
    "gn:population":0,
    "gn:timezone":"Africa/Blantyre",
    "iso:country":"MW",
    "wof:name":"Mphola",
    "wof:placetype":"locality"
},
  "geometry": {"coordinates":[34.81522,-14.66758],"type":"Point"}
}