{
  "type": "Feature",
  "properties": {
    "gn:admin1_code":"N",
    "gn:admin2_code":"21.0",
    "gn:asciiname":"Chiziwachapwa",
    "gn:country_code":"MW",
    "gn:dem":511,
    "gn:feature_class":"P",
    "gn:feature_code":"PPL",
    "gn:name":"Chiziwachapwa",
    "gn:population":0,
    "gn:timezone":"Africa/Blantyre",
    "iso:country":"MW",
    "wof:name":"Chiziwachapwa",
    "wof:placetype":"locality"
},
  "geometry": {"coordinates":[34.21278,-10.8883],"type":"Point"}
}