{
  "type": "Feature",
  "properties": {
    "gn:admin1_code":"C",
    "gn:admin2_code":"22.0",
    "gn:asciiname":"Bandawe",
    "gn:country_code":"MW",
    "gn:dem":476,
    "gn:feature_class":"P",
    "gn:feature_code":"PPL",
    "gn:name":"Bandawe",
    "gn:population":0,
    "gn:timezone":"Africa/Blantyre",
    "iso:country":"MW",
    "name:fra_x_preferred":[
        "Bandawe"
    ],
    "wof:name":"Bandawe",
    "wof:placetype":"locality"
},
  "geometry": {"coordinates":[34.59514,-13.68567],"type":"Point"}
}