{
  "type": "Feature",
  "properties": {
    "gn:admin1_code":"C",
    "gn:admin2_code":"11.0",
    "gn:asciiname":"Kampanikiza",
    "gn:country_code":"MW",
    "gn:dem":1222,
    "gn:feature_class":"P",
    "gn:feature_code":"PPL",
    "gn:name":"Kampanikiza",
    "gn:population":0,
    "gn:timezone":"Africa/Blantyre",
    "iso:country":"MW",
    "name:und_x_variant":[
        "Kampanizita",
        "Kampanikiza"
    ],
    "wof:name":"Kampanikiza",
    "wof:placetype":"locality"
},
  "geometry": {"coordinates":[33.71892,-14.34248],"type":"Point"}
}