{
  "type": "Feature",
  "properties": {
    "gn:admin1_code":"N",
    "gn:admin2_code":"15.0",
    "gn:asciiname":"Bulala",
    "gn:country_code":"MW",
    "gn:dem":1276,
    "gn:feature_class":"P",
    "gn:feature_code":"PPL",
    "gn:name":"Bulala",
    "gn:population":0,
    "gn:timezone":"Africa/Blantyre",
    "iso:country":"MW",
    "name:eng_x_preferred":[
        "Bulala"
    ],
    "wof:name":"Bulala",
    "wof:placetype":"locality"
},
  "geometry": {"coordinates":[33.44657,-11.67769],"type":"Point"}
}