{
  "type": "Feature",
  "properties": {
    "gn:admin1_code":"S",
    "gn:admin2_code":"28.0",
    "gn:asciiname":"Maluma",
    "gn:country_code":"MW",
    "gn:dem":536,
    "gn:feature_class":"P",
    "gn:feature_code":"PPL",
    "gn:name":"Maluma",
    "gn:population":0,
    "gn:timezone":"Africa/Blantyre",
    "iso:country":"MW",
    "name:deu_x_preferred":[
        "Maluma"
    ],
    "name:ita_x_preferred":[
        "Maluma"
    ],
    "name:msa_x_preferred":[
        "Maluma"
    ],
    "name:swe_x_preferred":[
        "Maluma"
    ],
    "name:tur_x_preferred":[
        "Maluma"
    ],
    "wof:name":"Maluma",
    "wof:placetype":"locality"
},
  "geometry": {"coordinates":[35.42485999999999,-14.94231],"type":"Point"}
}