{
  "type": "Feature",
  "properties": {
    "gn:admin1_code":"S",
    "gn:admin2_code":"23.0",
    "gn:asciiname":"Muruma Settlement",
    "gn:country_code":"MW",
    "gn:dem":728,
    "gn:feature_class":"P",
    "gn:feature_code":"PPL",
    "gn:name":"Muruma Settlement",
    "gn:population":0,
    "gn:timezone":"Africa/Blantyre",
    "iso:country":"MW",
    "wof:name":"Muruma Settlement",
    "wof:placetype":"locality"
},
  "geometry": {"coordinates":[35.41667,-15.58333],"type":"Point"}
}