{
  "type": "Feature",
  "properties": {
    "iso:country":"MW",
    "name:azb_x_preferred":[
        "\u062f\u0648\u0648\u0627"
    ],
    "name:cat_x_preferred":[
        "Dowa"
    ],
    "name:ceb_x_preferred":[
        "Dowa"
    ],
    "name:dan_x_preferred":[
        "Dowa"
    ],
    "name:deu_x_preferred":[
        "Dowa"
    ],
    "name:eng_x_preferred":[
        "Dowa"
    ],
    "name:fas_x_preferred":[
        "\u062f\u0648\u0648\u0627"
    ],
    "name:fra_x_preferred":[
        "Dowa"
    ],
    "name:heb_x_preferred":[
        "\u05d3\u05d5\u05d5\u05d4"
    ],
    "name:hun_x_preferred":[
        "Dowa"
    ],
    "name:ita_x_preferred":[
        "Dowa"
    ],
    "name:jpn_x_preferred":[
        "\u30c9\u30fc\u30ef"
    ],
    "name:nld_x_preferred":[
        "Dowa"
    ],
    "name:nya_x_preferred":[
        "Dowa"
    ],
    "name:pol_x_preferred":[
        "Dowa"
    ],
    "name:por_x_preferred":[
        "Dowa"
    ],
    "name:swa_x_preferred":[
        "Dowa"
    ],
    "name:swe_x_preferred":[
        "Dowa"
    ],
    "name:tur_x_preferred":[
        "Dowa"
    ],
    "name:zho_x_preferred":[
        "\u591a\u74e6"
    ],
    "name:zul_x_preferred":[
        "Dowa"
    ],
    "qs:gn_country":"MW",
    "qs:gn_fcode":"PPLA2",
    "qs:gn_pop":5565,
    "qs:name":"Dowa",
    "qs:name_adm0":"Malawi",
    "qs:name_adm1":"Dowa",
    "qs:photos":0,
    "qs:photos_1k":0,
    "qs:photos_9k":1,
    "qs:photos_9r":1,
    "qs:photos_all":5,
    "qs:photos_sr":0,
    "qs:placetype":"Town",
    "qs:pop_sr":"5",
    "qs:woe_adm0":23424889,
    "wof:name":"Dowa",
    "wof:placetype":"locality",
    "wof:population":5565
},
  "geometry": {"coordinates":[33.93754,-13.65399],"type":"Point"}
}