{
  "type": "Feature",
  "properties": {
    "gn:admin1_code":"S",
    "gn:admin2_code":"25.0",
    "gn:asciiname":"Moffat",
    "gn:country_code":"MW",
    "gn:dem":391,
    "gn:feature_class":"P",
    "gn:feature_code":"PPL",
    "gn:name":"Moffat",
    "gn:population":0,
    "gn:timezone":"Africa/Blantyre",
    "iso:country":"MW",
    "name:bul_x_preferred":[
        "\u041c\u043e\u0444\u0430\u0442"
    ],
    "name:ceb_x_preferred":[
        "Moffat"
    ],
    "name:cym_x_preferred":[
        "Moffat"
    ],
    "name:deu_x_preferred":[
        "Moffat"
    ],
    "name:eus_x_preferred":[
        "Moffat"
    ],
    "name:fas_x_preferred":[
        "\u0645\u0648\u0641\u062a"
    ],
    "name:fra_x_preferred":[
        "Moffat"
    ],
    "name:gla_x_preferred":[
        "Mofad"
    ],
    "name:ita_x_preferred":[
        "Moffat"
    ],
    "name:sco_x_preferred":[
        "Moffat"
    ],
    "name:spa_x_preferred":[
        "Moffat"
    ],
    "name:swe_x_preferred":[
        "Moffat"
    ],
    "wof:name":"Moffat",
    "wof:placetype":"locality"
},
  "geometry": {"coordinates":[34.58204,-15.62454],"type":"Point"}
}