{
  "type": "Feature",
  "properties": {
    "gn:admin1_code":"S",
    "gn:admin2_code":"25.0",
    "gn:asciiname":"Moffat",
    "gn:country_code":"MW",
    "gn:dem":391,
    "gn:feature_class":"P",
    "gn:feature_code":"PPL",
    "gn:name":"Moffat",
    "gn:population":0,
    "gn:timezone":"Africa/Blantyre",
    "iso:country":"MW",
    "wof:name":"Moffat",
    "wof:placetype":"locality"
},
  "geometry": {"coordinates":[34.58204,-15.62454],"type":"Point"}
}