{
  "type": "Feature",
  "properties": {
    "gn:admin1_code":"S",
    "gn:admin2_code":"26.0",
    "gn:asciiname":"Celemu",
    "gn:country_code":"MW",
    "gn:dem":723,
    "gn:feature_class":"P",
    "gn:feature_code":"PPL",
    "gn:name":"Celemu",
    "gn:population":0,
    "gn:timezone":"Africa/Blantyre",
    "iso:country":"MW",
    "wof:name":"Celemu",
    "wof:placetype":"locality"
},
  "geometry": {"coordinates":[34.99659,-14.80384],"type":"Point"}
}