{
  "type": "Feature",
  "properties": {
    "gn:admin1_code":"N",
    "gn:admin2_code":"15.0",
    "gn:asciiname":"Mzoma",
    "gn:country_code":"MW",
    "gn:dem":1233,
    "gn:feature_class":"P",
    "gn:feature_code":"PPL",
    "gn:name":"Mzoma",
    "gn:population":0,
    "gn:timezone":"Africa/Blantyre",
    "iso:country":"MW",
    "wof:name":"Mzoma",
    "wof:placetype":"locality"
},
  "geometry": {"coordinates":[33.35,-12.15],"type":"Point"}
}