{
  "type": "Feature",
  "properties": {
    "gn:admin1_code":"C",
    "gn:admin2_code":"13.0",
    "gn:asciiname":"Chakuwara",
    "gn:country_code":"MW",
    "gn:dem":1093,
    "gn:feature_class":"P",
    "gn:feature_code":"PPL",
    "gn:name":"Chakuwara",
    "gn:population":0,
    "gn:timezone":"Africa/Blantyre",
    "iso:country":"MW",
    "wof:name":"Chakuwara",
    "wof:placetype":"locality"
},
  "geometry": {"coordinates":[33.15,-13.71667],"type":"Point"}
}