{
  "type": "Feature",
  "properties": {
    "gn:admin1_code":"S",
    "gn:admin2_code":"12.0",
    "gn:asciiname":"Chilipa",
    "gn:country_code":"MW",
    "gn:dem":787,
    "gn:feature_class":"P",
    "gn:feature_code":"PPL",
    "gn:name":"Chilipa",
    "gn:population":0,
    "gn:timezone":"Africa/Blantyre",
    "iso:country":"MW",
    "wof:name":"Chilipa",
    "wof:placetype":"locality"
},
  "geometry": {"coordinates":[34.97792,-14.69802],"type":"Point"}
}