{
  "type": "Feature",
  "properties": {
    "gn:admin1_code":"N",
    "gn:admin2_code":"17.0",
    "gn:asciiname":"Goneka",
    "gn:country_code":"MW",
    "gn:dem":592,
    "gn:feature_class":"P",
    "gn:feature_code":"PPL",
    "gn:name":"Goneka",
    "gn:population":0,
    "gn:timezone":"Africa/Blantyre",
    "iso:country":"MW",
    "wof:name":"Goneka",
    "wof:placetype":"locality"
},
  "geometry": {"coordinates":[34.20381,-11.50482],"type":"Point"}
}