{
  "type": "Feature",
  "properties": {
    "gn:admin1_code":"S",
    "gn:admin2_code":"23.0",
    "gn:asciiname":"Chindambo",
    "gn:country_code":"MW",
    "gn:dem":974,
    "gn:feature_class":"P",
    "gn:feature_code":"PPL",
    "gn:name":"Chindambo",
    "gn:population":0,
    "gn:timezone":"Africa/Blantyre",
    "iso:country":"MW",
    "wof:name":"Chindambo",
    "wof:placetype":"locality"
},
  "geometry": {"coordinates":[35.28333,-15.46667],"type":"Point"}
}