{
  "type": "Feature",
  "properties": {
    "gn:admin1_code":"C",
    "gn:admin2_code":"6.0",
    "gn:asciiname":"Ntiwe",
    "gn:country_code":"MW",
    "gn:dem":1174,
    "gn:feature_class":"P",
    "gn:feature_code":"PPL",
    "gn:name":"Ntiwe",
    "gn:population":0,
    "gn:timezone":"Africa/Blantyre",
    "iso:country":"MW",
    "wof:name":"Ntiwe",
    "wof:placetype":"locality"
},
  "geometry": {"coordinates":[34.3215,-14.12698],"type":"Point"}
}