{
  "type": "Feature",
  "properties": {
    "gn:admin1_code":"C",
    "gn:admin2_code":"6.0",
    "gn:asciiname":"Chagwalugwa",
    "gn:country_code":"MW",
    "gn:dem":1306,
    "gn:feature_class":"P",
    "gn:feature_code":"PPL",
    "gn:name":"Chagwalugwa",
    "gn:population":0,
    "gn:timezone":"Africa/Blantyre",
    "iso:country":"MW",
    "wof:name":"Chagwalugwa",
    "wof:placetype":"locality"
},
  "geometry": {"coordinates":[34.08333,-14.45],"type":"Point"}
}