{
  "type": "Feature",
  "properties": {
    "gn:admin1_code":"C",
    "gn:admin2_code":"9.0",
    "gn:asciiname":"Nkakomiala",
    "gn:country_code":"MW",
    "gn:dem":1153,
    "gn:feature_class":"P",
    "gn:feature_code":"PPL",
    "gn:name":"Nkakomiala",
    "gn:population":0,
    "gn:timezone":"Africa/Blantyre",
    "iso:country":"MW",
    "wof:name":"Nkakomiala",
    "wof:placetype":"locality"
},
  "geometry": {"coordinates":[33.58333,-13.08333],"type":"Point"}
}