{
  "type": "Feature",
  "properties": {
    "gn:admin1_code":"C",
    "gn:admin2_code":"11.0",
    "gn:asciiname":"Bowa",
    "gn:country_code":"MW",
    "gn:dem":1195,
    "gn:feature_class":"P",
    "gn:feature_code":"PPL",
    "gn:name":"Bowa",
    "gn:population":0,
    "gn:timezone":"Africa/Blantyre",
    "iso:country":"MW",
    "name:ceb_x_preferred":[
        "Bowa"
    ],
    "name:swe_x_preferred":[
        "Bowa"
    ],
    "wof:name":"Bowa",
    "wof:placetype":"locality"
},
  "geometry": {"coordinates":[33.75,-13.78333],"type":"Point"}
}