{
  "type": "Feature",
  "properties": {
    "gn:admin1_code":"N",
    "gn:admin2_code":"15.0",
    "gn:asciiname":"Saulosi Mkosi",
    "gn:country_code":"MW",
    "gn:dem":1288,
    "gn:feature_class":"P",
    "gn:feature_code":"PPL",
    "gn:name":"Saulosi Mkosi",
    "gn:population":0,
    "gn:timezone":"Africa/Blantyre",
    "iso:country":"MW",
    "wof:name":"Saulosi Mkosi",
    "wof:placetype":"locality"
},
  "geometry": {"coordinates":[33.82269,-11.42771],"type":"Point"}
}