{
  "type": "Feature",
  "properties": {
    "gn:admin1_code":"N",
    "gn:admin2_code":"15.0",
    "gn:asciiname":"Jonasi Lowora",
    "gn:country_code":"MW",
    "gn:dem":1318,
    "gn:feature_class":"P",
    "gn:feature_code":"PPL",
    "gn:name":"Jonasi Lowora",
    "gn:population":0,
    "gn:timezone":"Africa/Blantyre",
    "iso:country":"MW",
    "wof:name":"Jonasi Lowora",
    "wof:placetype":"locality"
},
  "geometry": {"coordinates":[33.52691,-11.85143],"type":"Point"}
}