{
  "type": "Feature",
  "properties": {
    "gn:admin1_code":"N",
    "gn:admin2_code":"15.0",
    "gn:asciiname":"Kampoti",
    "gn:country_code":"MW",
    "gn:dem":1391,
    "gn:feature_class":"P",
    "gn:feature_code":"PPL",
    "gn:name":"Kampoti",
    "gn:population":0,
    "gn:timezone":"Africa/Blantyre",
    "iso:country":"MW",
    "wof:name":"Kampoti",
    "wof:placetype":"locality"
},
  "geometry": {"coordinates":[33.7386,-12.48506],"type":"Point"}
}