{
  "type": "Feature",
  "properties": {
    "gn:admin1_code":"S",
    "gn:admin2_code":"2.0",
    "gn:asciiname":"Alimenda",
    "gn:country_code":"MW",
    "gn:dem":145,
    "gn:feature_class":"P",
    "gn:feature_code":"PPL",
    "gn:name":"Alimenda",
    "gn:population":0,
    "gn:timezone":"Africa/Blantyre",
    "iso:country":"MW",
    "wof:name":"Alimenda",
    "wof:placetype":"locality"
},
  "geometry": {"coordinates":[34.66936,-16.22373],"type":"Point"}
}