{
  "type": "Feature",
  "properties": {
    "gn:admin1_code":"C",
    "gn:admin2_code":"20.0",
    "gn:asciiname":"Mkhuzi",
    "gn:country_code":"MW",
    "gn:dem":1237,
    "gn:feature_class":"P",
    "gn:feature_code":"PPL",
    "gn:name":"Mkhuzi",
    "gn:population":0,
    "gn:timezone":"Africa/Blantyre",
    "iso:country":"MW",
    "wof:name":"Mkhuzi",
    "wof:placetype":"locality"
},
  "geometry": {"coordinates":[33.76599,-13.36915],"type":"Point"}
}