{
  "type": "Feature",
  "properties": {
    "gn:admin1_code":"S",
    "gn:admin2_code":"31.0",
    "gn:asciiname":"Ndelema",
    "gn:country_code":"MW",
    "gn:dem":306,
    "gn:feature_class":"P",
    "gn:feature_code":"PPL",
    "gn:name":"Ndelema",
    "gn:population":0,
    "gn:timezone":"Africa/Blantyre",
    "iso:country":"MW",
    "wof:name":"Ndelema",
    "wof:placetype":"locality"
},
  "geometry": {"coordinates":[34.73662,-15.52014],"type":"Point"}
}