{
  "type": "Feature",
  "properties": {
    "gn:admin1_code":"N",
    "gn:admin2_code":"15.0",
    "gn:asciiname":"Chanamana Mwandira",
    "gn:country_code":"MW",
    "gn:dem":1307,
    "gn:feature_class":"P",
    "gn:feature_code":"PPL",
    "gn:name":"Chanamana Mwandira",
    "gn:population":0,
    "gn:timezone":"Africa/Blantyre",
    "iso:country":"MW",
    "name:eng_x_preferred":[
        "Chanamana Mwandira"
    ],
    "name:und_x_variant":[
        "Chandamana Mwandira"
    ],
    "wof:name":"Chanamana Mwandira",
    "wof:placetype":"locality"
},
  "geometry": {"coordinates":[33.46787,-11.65375],"type":"Point"}
}