{
  "type": "Feature",
  "properties": {
    "gn:admin1_code":"N",
    "gn:admin2_code":"21.0",
    "gn:asciiname":"Kanyenda Bondo",
    "gn:country_code":"MW",
    "gn:dem":1493,
    "gn:feature_class":"P",
    "gn:feature_code":"PPL",
    "gn:name":"Kanyenda Bondo",
    "gn:population":0,
    "gn:timezone":"Africa/Blantyre",
    "iso:country":"MW",
    "wof:name":"Kanyenda Bondo",
    "wof:placetype":"locality"
},
  "geometry": {"coordinates":[34.0496,-11.00542],"type":"Point"}
}