{
  "type": "Feature",
  "properties": {
    "gn:admin1_code":"C",
    "gn:admin2_code":"18.0",
    "gn:asciiname":"Njuwa",
    "gn:country_code":"MW",
    "gn:dem":479,
    "gn:feature_class":"P",
    "gn:feature_code":"PPL",
    "gn:name":"Njuwa",
    "gn:population":0,
    "gn:timezone":"Africa/Blantyre",
    "iso:country":"MW",
    "wof:name":"Njuwa",
    "wof:placetype":"locality"
},
  "geometry": {"coordinates":[34.01833,-12.23881],"type":"Point"}
}