{
  "type": "Feature",
  "properties": {
    "gn:admin1_code":"C",
    "gn:admin2_code":"16.0",
    "gn:asciiname":"Pulumuka",
    "gn:country_code":"MW",
    "gn:dem":726,
    "gn:feature_class":"P",
    "gn:feature_code":"PPL",
    "gn:name":"Pulumuka",
    "gn:population":0,
    "gn:timezone":"Africa/Blantyre",
    "iso:country":"MW",
    "wof:name":"Pulumuka",
    "wof:placetype":"locality"
},
  "geometry": {"coordinates":[34.91558,-14.90674],"type":"Point"}
}