{
  "type": "Feature",
  "properties": {
    "gn:admin1_code":"C",
    "gn:admin2_code":"9.0",
    "gn:asciiname":"Jonasi",
    "gn:country_code":"MW",
    "gn:dem":969,
    "gn:feature_class":"P",
    "gn:feature_code":"PPL",
    "gn:name":"Jonasi",
    "gn:population":0,
    "gn:timezone":"Africa/Blantyre",
    "iso:country":"MW",
    "wof:name":"Jonasi",
    "wof:placetype":"locality"
},
  "geometry": {"coordinates":[33.61556,-12.86173],"type":"Point"}
}