{
  "type": "Feature",
  "properties": {
    "gn:admin1_code":"C",
    "gn:admin2_code":"11.0",
    "gn:asciiname":"Gideon",
    "gn:country_code":"MW",
    "gn:dem":1219,
    "gn:feature_class":"P",
    "gn:feature_code":"PPL",
    "gn:name":"Gideon",
    "gn:population":0,
    "gn:timezone":"Africa/Blantyre",
    "iso:country":"MW",
    "name:ara_x_preferred":[
        "\u062c\u062f\u0639\u0648\u0646"
    ],
    "name:bul_x_preferred":[
        "\u0413\u0435\u0434\u0435\u043e\u043d"
    ],
    "name:cat_x_preferred":[
        "Gede\u00f3"
    ],
    "name:ces_x_preferred":[
        "Gede\u00f3n"
    ],
    "name:deu_x_preferred":[
        "Gideon"
    ],
    "name:ell_x_preferred":[
        "\u0393\u03b5\u03b4\u03b5\u03ce\u03bd"
    ],
    "name:epo_x_preferred":[
        "Gideon"
    ],
    "name:est_x_preferred":[
        "Gideon"
    ],
    "name:fas_x_preferred":[
        "\u062c\u062f\u0639\u0648\u0646"
    ],
    "name:fin_x_preferred":[
        "Gideon"
    ],
    "name:fra_x_preferred":[
        "G\u00e9d\u00e9on"
    ],
    "name:ind_x_preferred":[
        "Gideon"
    ],
    "name:ita_x_preferred":[
        "Gedeone"
    ],
    "name:jpn_x_preferred":[
        "\u30ae\u30c7\u30aa\u30f3"
    ],
    "name:kor_x_preferred":[
        "\uae30\ub4dc\uc628"
    ],
    "name:lit_x_preferred":[
        "Gideonas"
    ],
    "name:mlg_x_preferred":[
        "Gideona"
    ],
    "name:nld_x_preferred":[
        "Gideon"
    ],
    "name:nor_x_preferred":[
        "Gideon"
    ],
    "name:pnb_x_preferred":[
        "\u062c\u062f\u0639\u0648\u0646"
    ],
    "name:pol_x_preferred":[
        "Gedeon"
    ],
    "name:por_x_preferred":[
        "Gide\u00e3o"
    ],
    "name:ron_x_preferred":[
        "Ghedeon"
    ],
    "name:rus_x_preferred":[
        "\u0413\u0435\u0434\u0435\u043e\u043d"
    ],
    "name:sco_x_preferred":[
        "Gideon"
    ],
    "name:spa_x_preferred":[
        "Gede\u00f3n"
    ],
    "name:srp_x_preferred":[
        "\u0413\u0438\u0434\u0435\u043e\u043d"
    ],
    "name:swa_x_preferred":[
        "Gideoni"
    ],
    "name:swe_x_preferred":[
        "Gideon"
    ],
    "name:tgl_x_preferred":[
        "Gideon"
    ],
    "name:ukr_x_preferred":[
        "\u0413\u0435\u0434\u0435\u043e\u043d"
    ],
    "name:urd_x_preferred":[
        "\u062c\u062f\u0639\u0648\u0646"
    ],
    "wof:name":"Gideon",
    "wof:placetype":"locality"
},
  "geometry": {"coordinates":[33.68333,-14.43333],"type":"Point"}
}