{
  "type": "Feature",
  "properties": {
    "gn:admin1_code":"S",
    "gn:admin2_code":"29.0",
    "gn:asciiname":"Wendewende",
    "gn:country_code":"MW",
    "gn:dem":757,
    "gn:feature_class":"P",
    "gn:feature_code":"PPL",
    "gn:name":"Wendewende",
    "gn:population":0,
    "gn:timezone":"Africa/Blantyre",
    "iso:country":"MW",
    "wof:name":"Wendewende",
    "wof:placetype":"locality"
},
  "geometry": {"coordinates":[35.32737,-15.79224],"type":"Point"}
}