{
  "type": "Feature",
  "properties": {
    "gn:admin1_code":"C",
    "gn:admin2_code":"6.0",
    "gn:asciiname":"Ndebvu",
    "gn:country_code":"MW",
    "gn:dem":1252,
    "gn:feature_class":"P",
    "gn:feature_code":"PPL",
    "gn:name":"Ndebvu",
    "gn:population":0,
    "gn:timezone":"Africa/Blantyre",
    "iso:country":"MW",
    "wof:name":"Ndebvu",
    "wof:placetype":"locality"
},
  "geometry": {"coordinates":[33.91667,-14.45],"type":"Point"}
}