{
  "type": "Feature",
  "properties": {
    "gn:admin1_code":"N",
    "gn:admin2_code":"15.0",
    "gn:asciiname":"Ruben Mqongwani",
    "gn:country_code":"MW",
    "gn:dem":1072,
    "gn:feature_class":"P",
    "gn:feature_code":"PPL",
    "gn:name":"Ruben Mqongwani",
    "gn:population":0,
    "gn:timezone":"Africa/Blantyre",
    "iso:country":"MW",
    "wof:name":"Ruben Mqongwani",
    "wof:placetype":"locality"
},
  "geometry": {"coordinates":[33.86346,-11.13875],"type":"Point"}
}