{
  "type": "Feature",
  "properties": {
    "gn:admin1_code":"S",
    "gn:admin2_code":"2.0",
    "gn:asciiname":"Zironzo",
    "gn:country_code":"MW",
    "gn:dem":62,
    "gn:feature_class":"P",
    "gn:feature_code":"PPL",
    "gn:name":"Zironzo",
    "gn:population":0,
    "gn:timezone":"Africa/Blantyre",
    "iso:country":"MW",
    "wof:name":"Zironzo",
    "wof:placetype":"locality"
},
  "geometry": {"coordinates":[34.93333,-16.26667],"type":"Point"}
}