{
  "type": "Feature",
  "properties": {
    "gn:admin1_code":"C",
    "gn:admin2_code":"9.0",
    "gn:asciiname":"Bango",
    "gn:country_code":"MW",
    "gn:dem":1260,
    "gn:feature_class":"P",
    "gn:feature_code":"PPL",
    "gn:name":"Bango",
    "gn:population":0,
    "gn:timezone":"Africa/Blantyre",
    "iso:country":"MW",
    "name:ceb_x_preferred":[
        "Bango"
    ],
    "name:deu_x_preferred":[
        "Bango"
    ],
    "name:swe_x_preferred":[
        "Bango"
    ],
    "wof:name":"Bango",
    "wof:placetype":"locality"
},
  "geometry": {"coordinates":[33.41667,-12.55],"type":"Point"}
}