{
  "type": "Feature",
  "properties": {
    "gn:admin1_code":"C",
    "gn:admin2_code":"18.0",
    "gn:asciiname":"Chilibuno",
    "gn:country_code":"MW",
    "gn:dem":524,
    "gn:feature_class":"P",
    "gn:feature_code":"PPL",
    "gn:name":"Chilibuno",
    "gn:population":0,
    "gn:timezone":"Africa/Blantyre",
    "iso:country":"MW",
    "wof:name":"Chilibuno",
    "wof:placetype":"locality"
},
  "geometry": {"coordinates":[34.21399,-12.85674],"type":"Point"}
}