{
  "type": "Feature",
  "properties": {
    "gn:admin1_code":"S",
    "gn:admin2_code":"25.0",
    "gn:asciiname":"Chali",
    "gn:country_code":"MW",
    "gn:dem":643,
    "gn:feature_class":"P",
    "gn:feature_code":"PPL",
    "gn:name":"Chali",
    "gn:population":0,
    "gn:timezone":"Africa/Blantyre",
    "iso:country":"MW",
    "name:ita_x_preferred":[
        "Cali"
    ],
    "wof:name":"Chali",
    "wof:placetype":"locality"
},
  "geometry": {"coordinates":[34.40238,-15.73381],"type":"Point"}
}