{
  "type": "Feature",
  "properties": {
    "gn:admin1_code":"S",
    "gn:admin2_code":"28.0",
    "gn:asciiname":"Sombo",
    "gn:country_code":"MW",
    "gn:dem":770,
    "gn:feature_class":"P",
    "gn:feature_code":"PPL",
    "gn:name":"Sombo",
    "gn:population":0,
    "gn:timezone":"Africa/Blantyre",
    "iso:country":"MW",
    "wof:name":"Sombo",
    "wof:placetype":"locality"
},
  "geometry": {"coordinates":[35.65297,-14.65112],"type":"Point"}
}