{
  "type": "Feature",
  "properties": {
    "gn:admin1_code":"S",
    "gn:admin2_code":"28.0",
    "gn:asciiname":"Saleya",
    "gn:country_code":"MW",
    "gn:dem":643,
    "gn:feature_class":"P",
    "gn:feature_code":"PPL",
    "gn:name":"Saleya",
    "gn:population":0,
    "gn:timezone":"Africa/Blantyre",
    "iso:country":"MW",
    "wof:name":"Saleya",
    "wof:placetype":"locality"
},
  "geometry": {"coordinates":[35.81667,-14.78333],"type":"Point"}
}