{
  "type": "Feature",
  "properties": {
    "gn:admin1_code":"C",
    "gn:admin2_code":"20.0",
    "gn:asciiname":"Ngwata",
    "gn:country_code":"MW",
    "gn:dem":1119,
    "gn:feature_class":"P",
    "gn:feature_code":"PPL",
    "gn:name":"Ngwata",
    "gn:population":0,
    "gn:timezone":"Africa/Blantyre",
    "iso:country":"MW",
    "wof:name":"Ngwata",
    "wof:placetype":"locality"
},
  "geometry": {"coordinates":[34.03333,-13.46667],"type":"Point"}
}