{
  "type": "Feature",
  "properties": {
    "gn:admin1_code":"N",
    "gn:admin2_code":"15.0",
    "gn:asciiname":"Chimombo",
    "gn:country_code":"MW",
    "gn:dem":1021,
    "gn:feature_class":"P",
    "gn:feature_code":"PPL",
    "gn:name":"Chimombo",
    "gn:population":0,
    "gn:timezone":"Africa/Blantyre",
    "iso:country":"MW",
    "wof:name":"Chimombo",
    "wof:placetype":"locality"
},
  "geometry": {"coordinates":[33.94136,-11.00522],"type":"Point"}
}