{
  "type": "Feature",
  "properties": {
    "gn:admin1_code":"S",
    "gn:admin2_code":"19.0",
    "gn:asciiname":"Nhapali",
    "gn:country_code":"MW",
    "gn:dem":488,
    "gn:feature_class":"P",
    "gn:feature_code":"PPL",
    "gn:name":"Nhapali",
    "gn:population":0,
    "gn:timezone":"Africa/Blantyre",
    "iso:country":"MW",
    "wof:name":"Nhapali",
    "wof:placetype":"locality"
},
  "geometry": {"coordinates":[35.08349,-17.09718],"type":"Point"}
}