{
  "type": "Feature",
  "properties": {
    "gn:admin1_code":"S",
    "gn:admin2_code":"12.0",
    "gn:asciiname":"Meso",
    "gn:country_code":"MW",
    "gn:dem":509,
    "gn:feature_class":"P",
    "gn:feature_code":"PPL",
    "gn:name":"Meso",
    "gn:population":0,
    "gn:timezone":"Africa/Blantyre",
    "iso:country":"MW",
    "name:deu_x_preferred":[
        "Meso"
    ],
    "name:ell_x_preferred":[
        "\u039c\u03ad\u03c3\u03bf"
    ],
    "name:epo_x_preferred":[
        "Meso"
    ],
    "name:fra_x_preferred":[
        "M\u00e9so"
    ],
    "wof:name":"Meso",
    "wof:placetype":"locality"
},
  "geometry": {"coordinates":[35.34695,-14.55088],"type":"Point"}
}