{
  "type": "Feature",
  "properties": {
    "gn:admin1_code":"S",
    "gn:admin2_code":"26.0",
    "gn:asciiname":"Ligwangwa",
    "gn:country_code":"MW",
    "gn:dem":492,
    "gn:feature_class":"P",
    "gn:feature_code":"PPL",
    "gn:name":"Ligwangwa",
    "gn:population":0,
    "gn:timezone":"Africa/Blantyre",
    "iso:country":"MW",
    "wof:name":"Ligwangwa",
    "wof:placetype":"locality"
},
  "geometry": {"coordinates":[35.25080999999999,-14.84623],"type":"Point"}
}