{
  "type": "Feature",
  "properties": {
    "gn:admin1_code":"C",
    "gn:admin2_code":"7.0",
    "gn:asciiname":"Mawende",
    "gn:country_code":"MW",
    "gn:dem":836,
    "gn:feature_class":"P",
    "gn:feature_code":"PPL",
    "gn:name":"Mawende",
    "gn:population":0,
    "gn:timezone":"Africa/Blantyre",
    "iso:country":"MW",
    "wof:name":"Mawende",
    "wof:placetype":"locality"
},
  "geometry": {"coordinates":[34.11667,-13.65],"type":"Point"}
}