{
  "type": "Feature",
  "properties": {
    "gn:admin1_code":"S",
    "gn:admin2_code":"12.0",
    "gn:asciiname":"Kadango",
    "gn:country_code":"MW",
    "gn:dem":476,
    "gn:feature_class":"P",
    "gn:feature_code":"PPL",
    "gn:name":"Kadango",
    "gn:population":0,
    "gn:timezone":"Africa/Blantyre",
    "iso:country":"MW",
    "wof:name":"Kadango",
    "wof:placetype":"locality"
},
  "geometry": {"coordinates":[35.17663,-14.0915],"type":"Point"}
}