{
  "type": "Feature",
  "properties": {
    "gn:admin1_code":"N",
    "gn:admin2_code":"15.0",
    "gn:asciiname":"Mahowe",
    "gn:country_code":"MW",
    "gn:dem":1121,
    "gn:feature_class":"P",
    "gn:feature_code":"PPL",
    "gn:name":"Mahowe",
    "gn:population":0,
    "gn:timezone":"Africa/Blantyre",
    "iso:country":"MW",
    "wof:name":"Mahowe",
    "wof:placetype":"locality"
},
  "geometry": {"coordinates":[33.3743,-11.42751],"type":"Point"}
}