{
  "type": "Feature",
  "properties": {
    "gn:admin1_code":"N",
    "gn:admin2_code":"17.0",
    "gn:asciiname":"Mlenga Senga",
    "gn:country_code":"MW",
    "gn:dem":480,
    "gn:feature_class":"P",
    "gn:feature_code":"PPL",
    "gn:name":"Mlenga Senga",
    "gn:population":0,
    "gn:timezone":"Africa/Blantyre",
    "iso:country":"MW",
    "wof:name":"Mlenga Senga",
    "wof:placetype":"locality"
},
  "geometry": {"coordinates":[34.05321,-12.03512],"type":"Point"}
}