{
  "type": "Feature",
  "properties": {
    "gn:admin1_code":"S",
    "gn:admin2_code":"31.0",
    "gn:asciiname":"Khomera",
    "gn:country_code":"MW",
    "gn:dem":1149,
    "gn:feature_class":"P",
    "gn:feature_code":"PPL",
    "gn:name":"Khomera",
    "gn:population":0,
    "gn:timezone":"Africa/Blantyre",
    "iso:country":"MW",
    "wof:name":"Khomera",
    "wof:placetype":"locality"
},
  "geometry": {"coordinates":[34.57533,-15.40227],"type":"Point"}
}