{
  "type": "Feature",
  "properties": {
    "gn:admin1_code":"C",
    "gn:admin2_code":"16.0",
    "gn:asciiname":"Ondwe",
    "gn:country_code":"MW",
    "gn:dem":648,
    "gn:feature_class":"P",
    "gn:feature_code":"PPL",
    "gn:name":"Ondwe",
    "gn:population":0,
    "gn:timezone":"Africa/Blantyre",
    "iso:country":"MW",
    "wof:name":"Ondwe",
    "wof:placetype":"locality"
},
  "geometry": {"coordinates":[34.66667,-14.56667],"type":"Point"}
}