{
  "type": "Feature",
  "properties": {
    "gn:admin1_code":"N",
    "gn:admin2_code":"15.0",
    "gn:asciiname":"Jamu Kumwenda",
    "gn:country_code":"MW",
    "gn:dem":1373,
    "gn:feature_class":"P",
    "gn:feature_code":"PPL",
    "gn:name":"Jamu Kumwenda",
    "gn:population":0,
    "gn:timezone":"Africa/Blantyre",
    "iso:country":"MW",
    "wof:name":"Jamu Kumwenda",
    "wof:placetype":"locality"
},
  "geometry": {"coordinates":[33.52309,-12.12857],"type":"Point"}
}