{
  "type": "Feature",
  "properties": {
    "gn:admin1_code":"C",
    "gn:admin2_code":"7.0",
    "gn:asciiname":"Kasamba",
    "gn:country_code":"MW",
    "gn:dem":1249,
    "gn:feature_class":"P",
    "gn:feature_code":"PPL",
    "gn:name":"Kasamba",
    "gn:population":0,
    "gn:timezone":"Africa/Blantyre",
    "iso:country":"MW",
    "wof:name":"Kasamba",
    "wof:placetype":"locality"
},
  "geometry": {"coordinates":[33.71667,-13.45],"type":"Point"}
}