{
  "type": "Feature",
  "properties": {
    "gn:admin1_code":"C",
    "gn:admin2_code":"13.0",
    "gn:asciiname":"Kamwendo",
    "gn:country_code":"MW",
    "gn:dem":1138,
    "gn:feature_class":"P",
    "gn:feature_code":"PPL",
    "gn:name":"Kamwendo",
    "gn:population":0,
    "gn:timezone":"Africa/Blantyre",
    "iso:country":"MW",
    "wof:name":"Kamwendo",
    "wof:placetype":"locality"
},
  "geometry": {"coordinates":[33.04620999999999,-13.82921],"type":"Point"}
}