{
  "type": "Feature",
  "properties": {
    "gn:admin1_code":"C",
    "gn:admin2_code":"13.0",
    "gn:asciiname":"Chitumba",
    "gn:country_code":"MW",
    "gn:dem":1104,
    "gn:feature_class":"P",
    "gn:feature_code":"PPL",
    "gn:name":"Chitumba",
    "gn:population":0,
    "gn:timezone":"Africa/Blantyre",
    "iso:country":"MW",
    "wof:name":"Chitumba",
    "wof:placetype":"locality"
},
  "geometry": {"coordinates":[33.01965,-13.7707],"type":"Point"}
}