{
  "type": "Feature",
  "properties": {
    "gn:admin1_code":"C",
    "gn:admin2_code":"9.0",
    "gn:asciiname":"Mazuko",
    "gn:country_code":"MW",
    "gn:dem":1173,
    "gn:feature_class":"P",
    "gn:feature_code":"PPL",
    "gn:name":"Mazuko",
    "gn:population":0,
    "gn:timezone":"Africa/Blantyre",
    "iso:country":"MW",
    "wof:name":"Mazuko",
    "wof:placetype":"locality"
},
  "geometry": {"coordinates":[33.51667,-12.63333],"type":"Point"}
}