{
  "type": "Feature",
  "properties": {
    "gn:admin1_code":"C",
    "gn:admin2_code":"9.0",
    "gn:asciiname":"Chakhala II",
    "gn:country_code":"MW",
    "gn:dem":1060,
    "gn:feature_class":"P",
    "gn:feature_code":"PPL",
    "gn:name":"Chakhala II",
    "gn:population":0,
    "gn:timezone":"Africa/Blantyre",
    "iso:country":"MW",
    "wof:name":"Chakhala II",
    "wof:placetype":"locality"
},
  "geometry": {"coordinates":[33.3455,-13.31757],"type":"Point"}
}