{
  "type": "Feature",
  "properties": {
    "gn:admin1_code":"C",
    "gn:admin2_code":"20.0",
    "gn:asciiname":"Kawenda",
    "gn:country_code":"MW",
    "gn:dem":1255,
    "gn:feature_class":"P",
    "gn:feature_code":"PPL",
    "gn:name":"Kawenda",
    "gn:population":0,
    "gn:timezone":"Africa/Blantyre",
    "iso:country":"MW",
    "wof:name":"Kawenda",
    "wof:placetype":"locality"
},
  "geometry": {"coordinates":[33.81667,-13.35],"type":"Point"}
}