{
  "type": "Feature",
  "properties": {
    "gn:admin1_code":"N",
    "gn:admin2_code":"4.0",
    "gn:asciiname":"Sikana",
    "gn:country_code":"MW",
    "gn:dem":1246,
    "gn:feature_class":"P",
    "gn:feature_code":"PPL",
    "gn:name":"Sikana",
    "gn:population":0,
    "gn:timezone":"Africa/Blantyre",
    "iso:country":"MW",
    "name:eng_x_preferred":[
        "Sikana"
    ],
    "name:eng_x_variant":[
        "Nchumbe"
    ],
    "name:und_x_variant":[
        "Shikana"
    ],
    "wof:name":"Sikana",
    "wof:placetype":"locality"
},
  "geometry": {"coordinates":[33.26130999999999,-9.74954],"type":"Point"}
}