{
  "type": "Feature",
  "properties": {
    "gn:admin1_code":"C",
    "gn:admin2_code":"7.0",
    "gn:asciiname":"Ndembo",
    "gn:country_code":"MW",
    "gn:dem":1191,
    "gn:feature_class":"P",
    "gn:feature_code":"PPL",
    "gn:name":"Ndembo",
    "gn:population":0,
    "gn:timezone":"Africa/Blantyre",
    "iso:country":"MW",
    "wof:name":"Ndembo",
    "wof:placetype":"locality"
},
  "geometry": {"coordinates":[33.68333,-13.41667],"type":"Point"}
}