{
  "type": "Feature",
  "properties": {
    "gn:admin1_code":"N",
    "gn:admin2_code":"15.0",
    "gn:asciiname":"Kambewa",
    "gn:country_code":"MW",
    "gn:dem":1223,
    "gn:feature_class":"P",
    "gn:feature_code":"PPL",
    "gn:name":"Kambewa",
    "gn:population":0,
    "gn:timezone":"Africa/Blantyre",
    "iso:country":"MW",
    "wof:name":"Kambewa",
    "wof:placetype":"locality"
},
  "geometry": {"coordinates":[33.26667,-12.11667],"type":"Point"}
}