{
  "type": "Feature",
  "properties": {
    "gn:admin1_code":"N",
    "gn:admin2_code":"15.0",
    "gn:asciiname":"Eutini",
    "gn:country_code":"MW",
    "gn:dem":1162,
    "gn:feature_class":"P",
    "gn:feature_code":"PPL",
    "gn:name":"Eutini",
    "gn:population":0,
    "gn:timezone":"Africa/Blantyre",
    "iso:country":"MW",
    "wof:name":"Eutini",
    "wof:placetype":"locality"
},
  "geometry": {"coordinates":[33.42189,-11.46506],"type":"Point"}
}