{
  "type": "Feature",
  "properties": {
    "gn:admin1_code":"S",
    "gn:admin2_code":"24.0",
    "gn:asciiname":"Chiwembe",
    "gn:country_code":"MW",
    "gn:dem":1118,
    "gn:feature_class":"P",
    "gn:feature_code":"PPL",
    "gn:name":"Chiwembe",
    "gn:population":0,
    "gn:timezone":"Africa/Blantyre",
    "iso:country":"MW",
    "wof:name":"Chiwembe",
    "wof:placetype":"locality"
},
  "geometry": {"coordinates":[35.05087,-15.83437],"type":"Point"}
}