{
  "type": "Feature",
  "properties": {
    "gn:admin1_code":"C",
    "gn:admin2_code":"11.0",
    "gn:asciiname":"Ndalama",
    "gn:country_code":"MW",
    "gn:dem":1137,
    "gn:feature_class":"P",
    "gn:feature_code":"PPL",
    "gn:name":"Ndalama",
    "gn:population":0,
    "gn:timezone":"Africa/Blantyre",
    "iso:country":"MW",
    "wof:name":"Ndalama",
    "wof:placetype":"locality"
},
  "geometry": {"coordinates":[33.41667,-13.73333],"type":"Point"}
}