{
  "type": "Feature",
  "properties": {
    "gn:admin1_code":"C",
    "gn:admin2_code":"11.0",
    "gn:asciiname":"Njewa",
    "gn:country_code":"MW",
    "gn:dem":1093,
    "gn:feature_class":"P",
    "gn:feature_code":"PPL",
    "gn:name":"Njewa",
    "gn:population":0,
    "gn:timezone":"Africa/Blantyre",
    "iso:country":"MW",
    "name:und_x_variant":[
        "Njawa",
        "Njewa"
    ],
    "wof:name":"Njewa",
    "wof:placetype":"locality"
},
  "geometry": {"coordinates":[33.71667,-13.98333],"type":"Point"}
}