{
  "type": "Feature",
  "properties": {
    "gn:admin1_code":"C",
    "gn:admin2_code":"18.0",
    "gn:asciiname":"Kapanga",
    "gn:country_code":"MW",
    "gn:dem":476,
    "gn:feature_class":"P",
    "gn:feature_code":"PPL",
    "gn:name":"Kapanga",
    "gn:population":0,
    "gn:timezone":"Africa/Blantyre",
    "iso:country":"MW",
    "name:ceb_x_preferred":[
        "Kapanga"
    ],
    "name:fra_x_preferred":[
        "Kapanga"
    ],
    "name:nld_x_preferred":[
        "Kapanga"
    ],
    "name:spa_x_preferred":[
        "Kapanga"
    ],
    "name:swe_x_preferred":[
        "Kapanga"
    ],
    "name:vie_x_preferred":[
        "Kapanga"
    ],
    "name:war_x_preferred":[
        "Kapanga"
    ],
    "wof:name":"Kapanga",
    "wof:placetype":"locality"
},
  "geometry": {"coordinates":[34.33333,-13.05],"type":"Point"}
}