{
  "type": "Feature",
  "properties": {
    "gn:admin1_code":"C",
    "gn:admin2_code":"18.0",
    "gn:asciiname":"Nkudzula",
    "gn:country_code":"MW",
    "gn:dem":485,
    "gn:feature_class":"P",
    "gn:feature_code":"PPL",
    "gn:name":"Nkudzula",
    "gn:population":0,
    "gn:timezone":"Africa/Blantyre",
    "iso:country":"MW",
    "wof:name":"Nkudzula",
    "wof:placetype":"locality"
},
  "geometry": {"coordinates":[34.26667,-13.13333],"type":"Point"}
}