{
  "type": "Feature",
  "properties": {
    "gn:admin1_code":"N",
    "gn:admin2_code":"15.0",
    "gn:asciiname":"Matomora Chadewa",
    "gn:country_code":"MW",
    "gn:dem":1347,
    "gn:feature_class":"P",
    "gn:feature_code":"PPL",
    "gn:name":"Matomora Chadewa",
    "gn:population":0,
    "gn:timezone":"Africa/Blantyre",
    "iso:country":"MW",
    "wof:name":"Matomora Chadewa",
    "wof:placetype":"locality"
},
  "geometry": {"coordinates":[33.5014,-11.70361],"type":"Point"}
}