{
  "type": "Feature",
  "properties": {
    "gn:admin1_code":"C",
    "gn:admin2_code":"9.0",
    "gn:asciiname":"Gwesele",
    "gn:country_code":"MW",
    "gn:dem":1067,
    "gn:feature_class":"P",
    "gn:feature_code":"PPL",
    "gn:name":"Gwesele",
    "gn:population":0,
    "gn:timezone":"Africa/Blantyre",
    "iso:country":"MW",
    "wof:name":"Gwesele",
    "wof:placetype":"locality"
},
  "geometry": {"coordinates":[33.49597,-13.20524],"type":"Point"}
}