{
  "type": "Feature",
  "properties": {
    "gn:admin1_code":"N",
    "gn:admin2_code":"27.0",
    "gn:asciiname":"Mbungu",
    "gn:country_code":"MW",
    "gn:dem":552,
    "gn:feature_class":"P",
    "gn:feature_code":"PPL",
    "gn:name":"Mbungu",
    "gn:population":0,
    "gn:timezone":"Africa/Blantyre",
    "iso:country":"MW",
    "wof:name":"Mbungu",
    "wof:placetype":"locality"
},
  "geometry": {"coordinates":[34.71667,-12.08333],"type":"Point"}
}