{
  "type": "Feature",
  "properties": {
    "gn:admin1_code":"N",
    "gn:admin2_code":"4.0",
    "gn:asciiname":"Neaweane",
    "gn:country_code":"MW",
    "gn:dem":1010,
    "gn:feature_class":"P",
    "gn:feature_code":"PPL",
    "gn:name":"Neaweane",
    "gn:population":0,
    "gn:timezone":"Africa/Blantyre",
    "iso:country":"MW",
    "wof:name":"Neaweane",
    "wof:placetype":"locality"
},
  "geometry": {"coordinates":[33.56988,-9.61165],"type":"Point"}
}