{
  "type": "Feature",
  "properties": {
    "gn:admin1_code":"S",
    "gn:admin2_code":"5.0",
    "gn:asciiname":"Blair",
    "gn:country_code":"MW",
    "gn:dem":960,
    "gn:feature_class":"P",
    "gn:feature_code":"PPL",
    "gn:name":"Blair",
    "gn:population":0,
    "gn:timezone":"Africa/Blantyre",
    "iso:country":"MW",
    "name:ces_x_preferred":[
        "Blair"
    ],
    "name:deu_x_preferred":[
        "Blair"
    ],
    "name:gla_x_preferred":[
        "Bl\u00e0r"
    ],
    "name:slv_x_preferred":[
        "Blair"
    ],
    "name:swe_x_preferred":[
        "Blair"
    ],
    "wof:name":"Blair",
    "wof:placetype":"locality"
},
  "geometry": {"coordinates":[35.12596,-16.07529],"type":"Point"}
}