{
  "type": "Feature",
  "properties": {
    "gn:admin1_code":"N",
    "gn:admin2_code":"21.0",
    "gn:asciiname":"Zun'guza",
    "gn:country_code":"MW",
    "gn:dem":1187,
    "gn:feature_class":"P",
    "gn:feature_code":"PPL",
    "gn:name":"Zun\u2019guza",
    "gn:population":0,
    "gn:timezone":"Africa/Blantyre",
    "iso:country":"MW",
    "wof:name":"Zun'guza",
    "wof:placetype":"locality"
},
  "geometry": {"coordinates":[33.58333,-11.0243],"type":"Point"}
}