{
  "type": "Feature",
  "properties": {
    "gn:admin1_code":"N",
    "gn:admin2_code":"21.0",
    "gn:asciiname":"Munyongo",
    "gn:country_code":"MW",
    "gn:dem":1024,
    "gn:feature_class":"P",
    "gn:feature_code":"PPL",
    "gn:name":"Munyongo",
    "gn:population":0,
    "gn:timezone":"Africa/Blantyre",
    "iso:country":"MW",
    "wof:name":"Munyongo",
    "wof:placetype":"locality"
},
  "geometry": {"coordinates":[33.98273,-10.91064],"type":"Point"}
}