{
  "type": "Feature",
  "properties": {
    "gn:admin1_code":"C",
    "gn:admin2_code":"18.0",
    "gn:asciiname":"Mbuluma",
    "gn:country_code":"MW",
    "gn:dem":492,
    "gn:feature_class":"P",
    "gn:feature_code":"PPL",
    "gn:name":"Mbuluma",
    "gn:population":0,
    "gn:timezone":"Africa/Blantyre",
    "iso:country":"MW",
    "wof:name":"Mbuluma",
    "wof:placetype":"locality"
},
  "geometry": {"coordinates":[34.18577,-12.66112],"type":"Point"}
}