{
  "type": "Feature",
  "properties": {
    "gn:admin1_code":"C",
    "gn:admin2_code":"20.0",
    "gn:asciiname":"Chimponda",
    "gn:country_code":"MW",
    "gn:dem":1169,
    "gn:feature_class":"P",
    "gn:feature_code":"PPL",
    "gn:name":"Chimponda",
    "gn:population":0,
    "gn:timezone":"Africa/Blantyre",
    "iso:country":"MW",
    "wof:name":"Chimponda",
    "wof:placetype":"locality"
},
  "geometry": {"coordinates":[34.01667,-13.41667],"type":"Point"}
}