{
  "type": "Feature",
  "properties": {
    "gn:admin1_code":"S",
    "gn:admin2_code":"26.0",
    "gn:asciiname":"Nsunguliza",
    "gn:country_code":"MW",
    "gn:dem":626,
    "gn:feature_class":"P",
    "gn:feature_code":"PPL",
    "gn:name":"Nsunguliza",
    "gn:population":0,
    "gn:timezone":"Africa/Blantyre",
    "iso:country":"MW",
    "wof:name":"Nsunguliza",
    "wof:placetype":"locality"
},
  "geometry": {"coordinates":[34.96361,-14.93924],"type":"Point"}
}