{
  "type": "Feature",
  "properties": {
    "gn:admin1_code":"C",
    "gn:admin2_code":"6.0",
    "gn:asciiname":"Mnyanga",
    "gn:country_code":"MW",
    "gn:dem":1342,
    "gn:feature_class":"P",
    "gn:feature_code":"PPL",
    "gn:name":"Mnyanga",
    "gn:population":0,
    "gn:timezone":"Africa/Blantyre",
    "iso:country":"MW",
    "name:und_x_variant":[
        "Mhyanga",
        "Mnyanga"
    ],
    "wof:name":"Mnyanga",
    "wof:placetype":"locality"
},
  "geometry": {"coordinates":[34.17876,-14.31296],"type":"Point"}
}