{
  "type": "Feature",
  "properties": {
    "gn:admin1_code":"N",
    "gn:admin2_code":"4.0",
    "gn:asciiname":"Chiwanda",
    "gn:country_code":"MW",
    "gn:dem":1524,
    "gn:feature_class":"P",
    "gn:feature_code":"PPL",
    "gn:name":"Chiwanda",
    "gn:population":0,
    "gn:timezone":"Africa/Blantyre",
    "iso:country":"MW",
    "name:eng_x_preferred":[
        "Chiwanda"
    ],
    "wof:name":"Chiwanda",
    "wof:placetype":"locality"
},
  "geometry": {"coordinates":[33.49111,-9.71494],"type":"Point"}
}