{
  "type": "Feature",
  "properties": {
    "gn:admin1_code":"N",
    "gn:admin2_code":"15.0",
    "gn:asciiname":"Mpherapi Kumwenda",
    "gn:country_code":"MW",
    "gn:dem":1111,
    "gn:feature_class":"P",
    "gn:feature_code":"PPL",
    "gn:name":"Mpherapi Kumwenda",
    "gn:population":0,
    "gn:timezone":"Africa/Blantyre",
    "iso:country":"MW",
    "wof:name":"Mpherapi Kumwenda",
    "wof:placetype":"locality"
},
  "geometry": {"coordinates":[33.66184000000001,-11.15643],"type":"Point"}
}