{
  "type": "Feature",
  "properties": {
    "gn:admin1_code":"C",
    "gn:admin2_code":"16.0",
    "gn:asciiname":"Lizulu",
    "gn:country_code":"MW",
    "gn:dem":1451,
    "gn:feature_class":"P",
    "gn:feature_code":"PPL",
    "gn:name":"Lizulu",
    "gn:population":0,
    "gn:timezone":"Africa/Blantyre",
    "iso:country":"MW",
    "wof:name":"Lizulu",
    "wof:placetype":"locality"
},
  "geometry": {"coordinates":[34.46478,-14.51581],"type":"Point"}
}