{
  "type": "Feature",
  "properties": {
    "gn:admin1_code":"C",
    "gn:admin2_code":"16.0",
    "gn:asciiname":"Meja",
    "gn:country_code":"MW",
    "gn:dem":735,
    "gn:feature_class":"P",
    "gn:feature_code":"PPL",
    "gn:name":"Meja",
    "gn:population":0,
    "gn:timezone":"Africa/Blantyre",
    "iso:country":"MW",
    "name:dan_x_preferred":[
        "Meja"
    ],
    "name:deu_x_preferred":[
        "Meja"
    ],
    "name:fra_x_preferred":[
        "Meja"
    ],
    "name:ind_x_preferred":[
        "Meja"
    ],
    "name:isl_x_preferred":[
        "Meja"
    ],
    "name:ita_x_preferred":[
        "Meja"
    ],
    "name:jpn_x_preferred":[
        "\u30e1\u30a4\u30e4"
    ],
    "name:nld_x_preferred":[
        "Meja"
    ],
    "name:pol_x_preferred":[
        "Meja"
    ],
    "name:por_x_preferred":[
        "Meja"
    ],
    "name:rus_x_preferred":[
        "\u041c\u0435\u044f"
    ],
    "name:spa_x_preferred":[
        "Meja"
    ],
    "name:swe_x_preferred":[
        "Meja"
    ],
    "name:tur_x_preferred":[
        "Meja"
    ],
    "name:ukr_x_preferred":[
        "\u041c\u0435\u044f"
    ],
    "wof:name":"Meja",
    "wof:placetype":"locality"
},
  "geometry": {"coordinates":[34.86667,-14.85],"type":"Point"}
}