{
  "type": "Feature",
  "properties": {
    "gn:admin1_code":"C",
    "gn:admin2_code":"11.0",
    "gn:asciiname":"Nthesa",
    "gn:country_code":"MW",
    "gn:dem":1229,
    "gn:feature_class":"P",
    "gn:feature_code":"PPL",
    "gn:name":"Nthesa",
    "gn:population":0,
    "gn:timezone":"Africa/Blantyre",
    "iso:country":"MW",
    "wof:name":"Nthesa",
    "wof:placetype":"locality"
},
  "geometry": {"coordinates":[34.01667,-14.11667],"type":"Point"}
}