{
  "type": "Feature",
  "properties": {
    "gn:admin1_code":"N",
    "gn:admin2_code":"15.0",
    "gn:asciiname":"Magido",
    "gn:country_code":"MW",
    "gn:dem":1153,
    "gn:feature_class":"P",
    "gn:feature_code":"PPL",
    "gn:name":"Magido",
    "gn:population":0,
    "gn:timezone":"Africa/Blantyre",
    "iso:country":"MW",
    "name:eng_x_preferred":[
        "Magido"
    ],
    "wof:name":"Magido",
    "wof:placetype":"locality"
},
  "geometry": {"coordinates":[33.35514000000001,-11.59975],"type":"Point"}
}