{
  "type": "Feature",
  "properties": {
    "gn:admin1_code":"C",
    "gn:admin2_code":"22.0",
    "gn:asciiname":"Chiselema",
    "gn:country_code":"MW",
    "gn:dem":634,
    "gn:feature_class":"P",
    "gn:feature_code":"PPL",
    "gn:name":"Chiselema",
    "gn:population":0,
    "gn:timezone":"Africa/Blantyre",
    "iso:country":"MW",
    "wof:name":"Chiselema",
    "wof:placetype":"locality"
},
  "geometry": {"coordinates":[34.32422,-13.88023],"type":"Point"}
}