{
  "type": "Feature",
  "properties": {
    "gn:admin1_code":"S",
    "gn:admin2_code":"12.0",
    "gn:asciiname":"Tambala",
    "gn:country_code":"MW",
    "gn:dem":849,
    "gn:feature_class":"P",
    "gn:feature_code":"PPL",
    "gn:name":"Tambala",
    "gn:population":0,
    "gn:timezone":"Africa/Blantyre",
    "iso:country":"MW",
    "wof:name":"Tambala",
    "wof:placetype":"locality"
},
  "geometry": {"coordinates":[35.56667,-14.45],"type":"Point"}
}