{
  "type": "Feature",
  "properties": {
    "gn:admin1_code":"C",
    "gn:admin2_code":"9.0",
    "gn:asciiname":"Zunguwa",
    "gn:country_code":"MW",
    "gn:dem":1261,
    "gn:feature_class":"P",
    "gn:feature_code":"PPL",
    "gn:name":"Zunguwa",
    "gn:population":0,
    "gn:timezone":"Africa/Blantyre",
    "iso:country":"MW",
    "wof:name":"Zunguwa",
    "wof:placetype":"locality"
},
  "geometry": {"coordinates":[33.45,-12.51667],"type":"Point"}
}