{
  "type": "Feature",
  "properties": {
    "gn:admin1_code":"C",
    "gn:admin2_code":"11.0",
    "gn:asciiname":"Mtandula",
    "gn:country_code":"MW",
    "gn:dem":1203,
    "gn:feature_class":"P",
    "gn:feature_code":"PPL",
    "gn:name":"Mtandula",
    "gn:population":0,
    "gn:timezone":"Africa/Blantyre",
    "iso:country":"MW",
    "wof:name":"Mtandula",
    "wof:placetype":"locality"
},
  "geometry": {"coordinates":[33.51667,-14.03333],"type":"Point"}
}