{
  "type": "Feature",
  "properties": {
    "gn:admin1_code":"C",
    "gn:admin2_code":"22.0",
    "gn:asciiname":"Katumba",
    "gn:country_code":"MW",
    "gn:dem":489,
    "gn:feature_class":"P",
    "gn:feature_code":"PPL",
    "gn:name":"Katumba",
    "gn:population":0,
    "gn:timezone":"Africa/Blantyre",
    "iso:country":"MW",
    "wof:name":"Katumba",
    "wof:placetype":"locality"
},
  "geometry": {"coordinates":[34.48333,-13.86667],"type":"Point"}
}