{
  "type": "Feature",
  "properties": {
    "gn:admin1_code":"C",
    "gn:admin2_code":"11.0",
    "gn:asciiname":"Filimoni",
    "gn:country_code":"MW",
    "gn:dem":1139,
    "gn:feature_class":"P",
    "gn:feature_code":"PPL",
    "gn:name":"Filimoni",
    "gn:population":0,
    "gn:timezone":"Africa/Blantyre",
    "iso:country":"MW",
    "wof:name":"Filimoni",
    "wof:placetype":"locality"
},
  "geometry": {"coordinates":[33.61667,-14.33333],"type":"Point"}
}