{
  "type": "Feature",
  "properties": {
    "gn:admin1_code":"C",
    "gn:admin2_code":"9.0",
    "gn:asciiname":"Zikheta",
    "gn:country_code":"MW",
    "gn:dem":1198,
    "gn:feature_class":"P",
    "gn:feature_code":"PPL",
    "gn:name":"Zikheta",
    "gn:population":0,
    "gn:timezone":"Africa/Blantyre",
    "iso:country":"MW",
    "wof:name":"Zikheta",
    "wof:placetype":"locality"
},
  "geometry": {"coordinates":[33.51573,-12.59275],"type":"Point"}
}