{
  "type": "Feature",
  "properties": {
    "gn:admin1_code":"S",
    "gn:admin2_code":"12.0",
    "gn:asciiname":"Chithumba",
    "gn:country_code":"MW",
    "gn:dem":482,
    "gn:feature_class":"P",
    "gn:feature_code":"PPL",
    "gn:name":"Chithumba",
    "gn:population":0,
    "gn:timezone":"Africa/Blantyre",
    "iso:country":"MW",
    "wof:name":"Chithumba",
    "wof:placetype":"locality"
},
  "geometry": {"coordinates":[35.29018,-14.77429],"type":"Point"}
}