{
  "type": "Feature",
  "properties": {
    "gn:admin1_code":"C",
    "gn:admin2_code":"9.0",
    "gn:asciiname":"Nduka",
    "gn:country_code":"MW",
    "gn:dem":994,
    "gn:feature_class":"P",
    "gn:feature_code":"PPL",
    "gn:name":"Nduka",
    "gn:population":0,
    "gn:timezone":"Africa/Blantyre",
    "iso:country":"MW",
    "wof:name":"Nduka",
    "wof:placetype":"locality"
},
  "geometry": {"coordinates":[33.5368,-12.88455],"type":"Point"}
}