{
  "type": "Feature",
  "properties": {
    "gn:admin1_code":"S",
    "gn:admin2_code":"30.0",
    "gn:asciiname":"Tuthuwa",
    "gn:country_code":"MW",
    "gn:dem":682,
    "gn:feature_class":"P",
    "gn:feature_code":"PPL",
    "gn:name":"Tuthuwa",
    "gn:population":0,
    "gn:timezone":"Africa/Blantyre",
    "iso:country":"MW",
    "wof:name":"Tuthuwa",
    "wof:placetype":"locality"
},
  "geometry": {"coordinates":[35.81182000000001,-15.84815],"type":"Point"}
}