{
  "type": "Feature",
  "properties": {
    "gn:admin1_code":"C",
    "gn:admin2_code":"13.0",
    "gn:asciiname":"Nyanjereze",
    "gn:country_code":"MW",
    "gn:dem":1134,
    "gn:feature_class":"P",
    "gn:feature_code":"PPL",
    "gn:name":"Nyanjereze",
    "gn:population":0,
    "gn:timezone":"Africa/Blantyre",
    "iso:country":"MW",
    "wof:name":"Nyanjereze",
    "wof:placetype":"locality"
},
  "geometry": {"coordinates":[32.96667,-13.83333],"type":"Point"}
}