{
  "type": "Feature",
  "properties": {
    "gn:admin1_code":"N",
    "gn:admin2_code":"15.0",
    "gn:asciiname":"Biambiri Mramu",
    "gn:country_code":"MW",
    "gn:dem":1224,
    "gn:feature_class":"P",
    "gn:feature_code":"PPL",
    "gn:name":"Biambiri Mramu",
    "gn:population":0,
    "gn:timezone":"Africa/Blantyre",
    "iso:country":"MW",
    "wof:name":"Biambiri Mramu",
    "wof:placetype":"locality"
},
  "geometry": {"coordinates":[33.7241,-11.46366],"type":"Point"}
}