{
  "type": "Feature",
  "properties": {
    "gn:admin1_code":"C",
    "gn:admin2_code":"22.0",
    "gn:asciiname":"Mikute",
    "gn:country_code":"MW",
    "gn:dem":514,
    "gn:feature_class":"P",
    "gn:feature_code":"PPL",
    "gn:name":"Mikute",
    "gn:population":0,
    "gn:timezone":"Africa/Blantyre",
    "iso:country":"MW",
    "wof:name":"Mikute",
    "wof:placetype":"locality"
},
  "geometry": {"coordinates":[34.58708,-13.75277],"type":"Point"}
}