{
  "type": "Feature",
  "properties": {
    "gn:admin1_code":"C",
    "gn:admin2_code":"13.0",
    "gn:asciiname":"Tikoliwe",
    "gn:country_code":"MW",
    "gn:dem":1324,
    "gn:feature_class":"P",
    "gn:feature_code":"PPL",
    "gn:name":"Tikoliwe",
    "gn:population":0,
    "gn:timezone":"Africa/Blantyre",
    "iso:country":"MW",
    "wof:name":"Tikoliwe",
    "wof:placetype":"locality"
},
  "geometry": {"coordinates":[32.79525,-13.77364],"type":"Point"}
}