{
  "type": "Feature",
  "properties": {
    "gn:country":"MW",
    "gn:fcode":"ADM2",
    "gn:pop":148763,
    "iso:country":"MW",
    "label:eng_x_preferred_longname":[
        "Mwanza District"
    ],
    "label:eng_x_preferred_placetype":[
        "district"
    ],
    "name:eng_x_preferred":[
        "Mwanza"
    ],
    "name:eng_x_variant":[
        "Mwanza District"
    ],
    "qs:name":"Mwanza District",
    "qs:photos_9r":0,
    "qs:photos_sr":0,
    "qs:pop_sr":"9",
    "wd:wordcount":174,
    "wof:name":"Mwanza",
    "wof:placetype":"county",
    "wof:placetype_local":"district",
    "wof:population":148763
},
  "geometry": {"coordinates":[34.51682,-15.63337],"type":"Point"}
}