{
  "type": "Feature",
  "properties": {
    "gn:admin1_code":"C",
    "gn:admin2_code":"18.0",
    "gn:asciiname":"Chawala",
    "gn:country_code":"MW",
    "gn:dem":480,
    "gn:feature_class":"P",
    "gn:feature_code":"PPL",
    "gn:name":"Chawala",
    "gn:population":0,
    "gn:timezone":"Africa/Blantyre",
    "iso:country":"MW",
    "name:und_x_variant":[
        "Chiwala",
        "Chawala"
    ],
    "wof:name":"Chawala",
    "wof:placetype":"locality"
},
  "geometry": {"coordinates":[34.1798,-12.55358],"type":"Point"}
}