{
  "type": "Feature",
  "properties": {
    "gn:admin1_code":"C",
    "gn:admin2_code":"13.0",
    "gn:asciiname":"Abraham",
    "gn:country_code":"MW",
    "gn:dem":1083,
    "gn:feature_class":"P",
    "gn:feature_code":"PPL",
    "gn:name":"Abraham",
    "gn:population":0,
    "gn:timezone":"Africa/Blantyre",
    "iso:country":"MW",
    "wof:name":"Abraham",
    "wof:placetype":"locality"
},
  "geometry": {"coordinates":[33.17007,-13.65751],"type":"Point"}
}