{
  "type": "Feature",
  "properties": {
    "gn:admin1_code":"N",
    "gn:admin2_code":"15.0",
    "gn:asciiname":"Chinombo",
    "gn:country_code":"MW",
    "gn:dem":1161,
    "gn:feature_class":"P",
    "gn:feature_code":"PPL",
    "gn:name":"Chinombo",
    "gn:population":0,
    "gn:timezone":"Africa/Blantyre",
    "iso:country":"MW",
    "wof:name":"Chinombo",
    "wof:placetype":"locality"
},
  "geometry": {"coordinates":[33.84297,-11.34036],"type":"Point"}
}