{
  "type": "Feature",
  "properties": {
    "gn:admin1_code":"S",
    "gn:admin2_code":"12.0",
    "gn:asciiname":"Chirando",
    "gn:country_code":"MW",
    "gn:dem":476,
    "gn:feature_class":"P",
    "gn:feature_code":"PPL",
    "gn:name":"Chirando",
    "gn:population":0,
    "gn:timezone":"Africa/Blantyre",
    "iso:country":"MW",
    "name:und_x_variant":[
        "Cherinda",
        "Chirando"
    ],
    "wof:name":"Chirando",
    "wof:placetype":"locality"
},
  "geometry": {"coordinates":[35.0619,-13.73865],"type":"Point"}
}