{
  "type": "Feature",
  "properties": {
    "gn:admin1_code":"N",
    "gn:admin2_code":"17.0",
    "gn:asciiname":"Kayuni",
    "gn:country_code":"MW",
    "gn:dem":1150,
    "gn:feature_class":"P",
    "gn:feature_code":"PPL",
    "gn:name":"Kayuni",
    "gn:population":0,
    "gn:timezone":"Africa/Blantyre",
    "iso:country":"MW",
    "wof:name":"Kayuni",
    "wof:placetype":"locality"
},
  "geometry": {"coordinates":[34.15402,-11.38173],"type":"Point"}
}