{
  "type": "Feature",
  "properties": {
    "gn:admin1_code":"C",
    "gn:admin2_code":"13.0",
    "gn:asciiname":"Chikuta",
    "gn:country_code":"MW",
    "gn:dem":1073,
    "gn:feature_class":"P",
    "gn:feature_code":"PPL",
    "gn:name":"Chikuta",
    "gn:population":0,
    "gn:timezone":"Africa/Blantyre",
    "iso:country":"MW",
    "wof:name":"Chikuta",
    "wof:placetype":"locality"
},
  "geometry": {"coordinates":[33.13333,-13.88333],"type":"Point"}
}