{
  "type": "Feature",
  "properties": {
    "gn:admin1_code":"C",
    "gn:admin2_code":"13.0",
    "gn:asciiname":"Gwedi",
    "gn:country_code":"MW",
    "gn:dem":1221,
    "gn:feature_class":"P",
    "gn:feature_code":"PPL",
    "gn:name":"Gwedi",
    "gn:population":0,
    "gn:timezone":"Africa/Blantyre",
    "iso:country":"MW",
    "wof:name":"Gwedi",
    "wof:placetype":"locality"
},
  "geometry": {"coordinates":[32.91246,-13.72316],"type":"Point"}
}