{
  "type": "Feature",
  "properties": {
    "gn:admin1_code":"C",
    "gn:admin2_code":"22.0",
    "gn:asciiname":"Lowe",
    "gn:country_code":"MW",
    "gn:dem":520,
    "gn:feature_class":"P",
    "gn:feature_code":"PPL",
    "gn:name":"Lowe",
    "gn:population":0,
    "gn:timezone":"Africa/Blantyre",
    "iso:country":"MW",
    "name:bel_x_preferred":[
        "\u041b\u043e\u0443"
    ],
    "name:ceb_x_preferred":[
        "Lowe"
    ],
    "name:ces_x_preferred":[
        "Lowe"
    ],
    "name:deu_x_preferred":[
        "Lowe"
    ],
    "name:fin_x_preferred":[
        "Lowe"
    ],
    "name:fra_x_preferred":[
        "Lowe"
    ],
    "name:ita_x_preferred":[
        "Lowe"
    ],
    "name:nld_x_preferred":[
        "Lowe"
    ],
    "name:pol_x_preferred":[
        "Lowe"
    ],
    "name:por_x_preferred":[
        "Lowe"
    ],
    "name:rus_x_preferred":[
        "Lowe"
    ],
    "name:swe_x_preferred":[
        "Lowe"
    ],
    "name:ukr_x_preferred":[
        "\u041b\u043e\u0443"
    ],
    "wof:name":"Lowe",
    "wof:placetype":"locality"
},
  "geometry": {"coordinates":[34.45,-13.91667],"type":"Point"}
}