{
  "type": "Feature",
  "properties": {
    "gn:admin1_code":"N",
    "gn:admin2_code":"15.0",
    "gn:asciiname":"Mteyo Ngoma",
    "gn:country_code":"MW",
    "gn:dem":1220,
    "gn:feature_class":"P",
    "gn:feature_code":"PPL",
    "gn:name":"Mteyo Ngoma",
    "gn:population":0,
    "gn:timezone":"Africa/Blantyre",
    "iso:country":"MW",
    "wof:name":"Mteyo Ngoma",
    "wof:placetype":"locality"
},
  "geometry": {"coordinates":[33.41667,-11.93333],"type":"Point"}
}