{
  "type": "Feature",
  "properties": {
    "iso:country":"MW",
    "name:bel_x_preferred":[
        "\u041a\u0430\u0441\u0443\u043d\u0433\u0443"
    ],
    "name:chi_x_preferred":[
        "\u5361\u677e\u53e4"
    ],
    "name:dan_x_preferred":[
        "Kasungu"
    ],
    "name:deu_x_preferred":[
        "Kasungu"
    ],
    "name:dut_x_preferred":[
        "Kasungu"
    ],
    "name:eng_x_preferred":[
        "Kasungu"
    ],
    "name:fas_x_preferred":[
        "\u06a9\u0627\u0633\u0648\u0646\u06af\u0648"
    ],
    "name:fra_x_preferred":[
        "Kasungu"
    ],
    "name:fre_x_preferred":[
        "Kasungu"
    ],
    "name:geo_x_preferred":[
        "\u10d9\u10d0\u10e1\u10e3\u10dc\u10d2\u10e3"
    ],
    "name:ger_x_preferred":[
        "Kasungu"
    ],
    "name:heb_x_preferred":[
        "\u05e7\u05e1\u05d5\u05e0\u05d2\u05d5"
    ],
    "name:ita_x_preferred":[
        "Kasungu"
    ],
    "name:jpn_x_preferred":[
        "\u30ab\u30b9\u30f3\u30b0"
    ],
    "name:kat_x_preferred":[
        "\u10d9\u10d0\u10e1\u10e3\u10dc\u10d2\u10e3"
    ],
    "name:kor_x_preferred":[
        "\uce74\uc22d\uad6c"
    ],
    "name:lit_x_preferred":[
        "Kasungu"
    ],
    "name:nld_x_preferred":[
        "Kasungu"
    ],
    "name:nya_x_preferred":[
        "Kasungu"
    ],
    "name:per_x_preferred":[
        "\u06a9\u0627\u0633\u0648\u0646\u06af\u0648"
    ],
    "name:pol_x_preferred":[
        "Kasungu"
    ],
    "name:por_x_preferred":[
        "Kasungu"
    ],
    "name:ron_x_preferred":[
        "Kasungu"
    ],
    "name:rum_x_preferred":[
        "Kasungu"
    ],
    "name:rus_x_preferred":[
        "\u041a\u0430\u0441\u0443\u043d\u0433\u0443"
    ],
    "name:spa_x_preferred":[
        "Kasungu"
    ],
    "name:swe_x_preferred":[
        "Kasungu"
    ],
    "name:tur_x_preferred":[
        "Kasungu"
    ],
    "name:zho_x_preferred":[
        "\u5361\u677e\u53e4"
    ],
    "qs:gn_country":"MW",
    "qs:gn_fcode":"PPLA2",
    "qs:gn_pop":42555,
    "qs:name":"Kasungu",
    "qs:name_adm0":"Malawi",
    "qs:name_adm1":"Kasungu",
    "qs:photos":0,
    "qs:photos_1k":0,
    "qs:photos_9k":1,
    "qs:photos_9r":1,
    "qs:photos_all":8,
    "qs:photos_sr":0,
    "qs:placetype":"Town",
    "qs:pop_sr":"7",
    "qs:woe_adm0":23424889,
    "wof:name":"Kasungu",
    "wof:placetype":"locality",
    "wof:population":42555
},
  "geometry": {"coordinates":[33.48333,-13.03333],"type":"Point"}
}