{
  "type": "Feature",
  "properties": {
    "gn:admin1_code":"C",
    "gn:admin2_code":"16.0",
    "gn:asciiname":"Kalitsilo",
    "gn:country_code":"MW",
    "gn:dem":1555,
    "gn:feature_class":"P",
    "gn:feature_code":"PPL",
    "gn:name":"Kalitsilo",
    "gn:population":0,
    "gn:timezone":"Africa/Blantyre",
    "iso:country":"MW",
    "name:und_x_variant":[
        "Camau",
        "Kalitsilo"
    ],
    "wof:name":"Kalitsilo",
    "wof:placetype":"locality"
},
  "geometry": {"coordinates":[34.53333,-14.58333],"type":"Point"}
}