{
  "type": "Feature",
  "properties": {
    "gn:admin1_code":"C",
    "gn:admin2_code":"16.0",
    "gn:asciiname":"Tambala",
    "gn:country_code":"MW",
    "gn:dem":663,
    "gn:feature_class":"P",
    "gn:feature_code":"PPL",
    "gn:name":"Tambala",
    "gn:population":0,
    "gn:timezone":"Africa/Blantyre",
    "iso:country":"MW",
    "wof:name":"Tambala",
    "wof:placetype":"locality"
},
  "geometry": {"coordinates":[34.85327,-14.74021],"type":"Point"}
}