{
  "type": "Feature",
  "properties": {
    "gn:admin1_code":"S",
    "gn:admin2_code":"29.0",
    "gn:asciiname":"Mimosa",
    "gn:country_code":"MW",
    "gn:dem":621,
    "gn:feature_class":"P",
    "gn:feature_code":"PPL",
    "gn:name":"Mimosa",
    "gn:population":0,
    "gn:timezone":"Africa/Blantyre",
    "iso:country":"MW",
    "wof:name":"Mimosa",
    "wof:placetype":"locality"
},
  "geometry": {"coordinates":[35.58443,-16.08151],"type":"Point"}
}