{
  "type": "Feature",
  "properties": {
    "gn:admin1_code":"S",
    "gn:admin2_code":"23.0",
    "gn:asciiname":"Chingali",
    "gn:country_code":"MW",
    "gn:dem":628,
    "gn:feature_class":"P",
    "gn:feature_code":"PPL",
    "gn:name":"Chingali",
    "gn:population":0,
    "gn:timezone":"Africa/Blantyre",
    "iso:country":"MW",
    "wof:name":"Chingali",
    "wof:placetype":"locality"
},
  "geometry": {"coordinates":[35.18277,-15.40003],"type":"Point"}
}