{
  "type": "Feature",
  "properties": {
    "gn:admin1_code":"C",
    "gn:admin2_code":"9.0",
    "gn:asciiname":"Cisuwula",
    "gn:country_code":"MW",
    "gn:dem":1003,
    "gn:feature_class":"P",
    "gn:feature_code":"PPL",
    "gn:name":"Cisuwula",
    "gn:population":0,
    "gn:timezone":"Africa/Blantyre",
    "iso:country":"MW",
    "wof:name":"Cisuwula",
    "wof:placetype":"locality"
},
  "geometry": {"coordinates":[33.35726,-12.87957],"type":"Point"}
}