{
  "type": "Feature",
  "properties": {
    "gn:admin1_code":"S",
    "gn:admin2_code":"23.0",
    "gn:asciiname":"Msosa",
    "gn:country_code":"MW",
    "gn:dem":1045,
    "gn:feature_class":"P",
    "gn:feature_code":"PPL",
    "gn:name":"Msosa",
    "gn:population":0,
    "gn:timezone":"Africa/Blantyre",
    "iso:country":"MW",
    "wof:name":"Msosa",
    "wof:placetype":"locality"
},
  "geometry": {"coordinates":[35.26667,-15.46667],"type":"Point"}
}