{
  "type": "Feature",
  "properties": {
    "gn:admin1_code":"S",
    "gn:admin2_code":"12.0",
    "gn:asciiname":"Kakowa",
    "gn:country_code":"MW",
    "gn:dem":895,
    "gn:feature_class":"P",
    "gn:feature_code":"PPL",
    "gn:name":"Kakowa",
    "gn:population":0,
    "gn:timezone":"Africa/Blantyre",
    "iso:country":"MW",
    "wof:name":"Kakowa",
    "wof:placetype":"locality"
},
  "geometry": {"coordinates":[35.55,-14.55],"type":"Point"}
}