{
  "type": "Feature",
  "properties": {
    "gn:admin1_code":"S",
    "gn:admin2_code":"23.0",
    "gn:asciiname":"Mkagula",
    "gn:country_code":"MW",
    "gn:dem":743,
    "gn:feature_class":"P",
    "gn:feature_code":"PPL",
    "gn:name":"Mkagula",
    "gn:population":0,
    "gn:timezone":"Africa/Blantyre",
    "iso:country":"MW",
    "wof:name":"Mkagula",
    "wof:placetype":"locality"
},
  "geometry": {"coordinates":[35.43333,-15.35],"type":"Point"}
}