{
  "type": "Feature",
  "properties": {
    "gn:admin1_code":"C",
    "gn:admin2_code":"13.0",
    "gn:asciiname":"Nelentino",
    "gn:country_code":"MW",
    "gn:dem":1094,
    "gn:feature_class":"P",
    "gn:feature_code":"PPL",
    "gn:name":"Nelentino",
    "gn:population":0,
    "gn:timezone":"Africa/Blantyre",
    "iso:country":"MW",
    "wof:name":"Nelentino",
    "wof:placetype":"locality"
},
  "geometry": {"coordinates":[33.15,-13.81667],"type":"Point"}
}