{
  "type": "Feature",
  "properties": {
    "gn:admin1_code":"C",
    "gn:admin2_code":"18.0",
    "gn:asciiname":"Kanunkha",
    "gn:country_code":"MW",
    "gn:dem":494,
    "gn:feature_class":"P",
    "gn:feature_code":"PPL",
    "gn:name":"Kanunkha",
    "gn:population":0,
    "gn:timezone":"Africa/Blantyre",
    "iso:country":"MW",
    "wof:name":"Kanunkha",
    "wof:placetype":"locality"
},
  "geometry": {"coordinates":[34.23333,-12.91667],"type":"Point"}
}