{
  "type": "Feature",
  "properties": {
    "gn:admin1_code":"N",
    "gn:admin2_code":"21.0",
    "gn:asciiname":"Zgambo",
    "gn:country_code":"MW",
    "gn:dem":1054,
    "gn:feature_class":"P",
    "gn:feature_code":"PPL",
    "gn:name":"Zgambo",
    "gn:population":0,
    "gn:timezone":"Africa/Blantyre",
    "iso:country":"MW",
    "wof:name":"Zgambo",
    "wof:placetype":"locality"
},
  "geometry": {"coordinates":[33.86667,-11.03333],"type":"Point"}
}