{
  "type": "Feature",
  "properties": {
    "gn:admin1_code":"C",
    "gn:admin2_code":"13.0",
    "gn:asciiname":"Menyani",
    "gn:country_code":"MW",
    "gn:dem":1240,
    "gn:feature_class":"P",
    "gn:feature_code":"PPL",
    "gn:name":"Menyani",
    "gn:population":0,
    "gn:timezone":"Africa/Blantyre",
    "iso:country":"MW",
    "wof:name":"Menyani",
    "wof:placetype":"locality"
},
  "geometry": {"coordinates":[32.83333,-13.76667],"type":"Point"}
}