{
  "type": "Feature",
  "properties": {
    "gn:admin1_code":"C",
    "gn:admin2_code":"9.0",
    "gn:asciiname":"John",
    "gn:country_code":"MW",
    "gn:dem":1092,
    "gn:feature_class":"P",
    "gn:feature_code":"PPL",
    "gn:name":"John",
    "gn:population":0,
    "gn:timezone":"Africa/Blantyre",
    "iso:country":"MW",
    "name:als_x_preferred":[
        "John"
    ],
    "name:ara_x_preferred":[
        "\u064a\u0648\u062d\u0646\u0627"
    ],
    "name:bre_x_preferred":[
        "John"
    ],
    "name:ceb_x_preferred":[
        "John"
    ],
    "name:ces_x_preferred":[
        "John"
    ],
    "name:deu_x_preferred":[
        "John"
    ],
    "name:fas_x_preferred":[
        "\u06cc\u0648\u062d\u0646\u0627"
    ],
    "name:fra_x_preferred":[
        "John"
    ],
    "name:heb_x_preferred":[
        "\u05d9\u05d5\u05d7\u05e0\u05df"
    ],
    "name:hye_x_preferred":[
        "\u054b\u0578\u0576"
    ],
    "name:ilo_x_preferred":[
        "John"
    ],
    "name:ind_x_preferred":[
        "John"
    ],
    "name:ita_x_preferred":[
        "John"
    ],
    "name:jpn_x_preferred":[
        "\u30e8\u30cf\u30cd"
    ],
    "name:nld_x_preferred":[
        "John"
    ],
    "name:rus_x_preferred":[
        "\u0414\u0436\u043e\u043d"
    ],
    "name:san_x_preferred":[
        "\u091c\u093e\u0939\u094d\u0928"
    ],
    "name:spa_x_preferred":[
        "John"
    ],
    "name:swe_x_preferred":[
        "John"
    ],
    "name:tam_x_preferred":[
        "\u0b9c\u0bbe\u0ba9\u0bcd"
    ],
    "name:tur_x_preferred":[
        "John"
    ],
    "name:ukr_x_preferred":[
        "\u0419\u043e\u043d"
    ],
    "name:vie_x_preferred":[
        "John"
    ],
    "wof:name":"John",
    "wof:placetype":"locality"
},
  "geometry": {"coordinates":[33.53333,-13.15],"type":"Point"}
}