{
  "type": "Feature",
  "properties": {
    "gn:admin1_code":"S",
    "gn:admin2_code":"28.0",
    "gn:asciiname":"Misi",
    "gn:country_code":"MW",
    "gn:dem":626,
    "gn:feature_class":"P",
    "gn:feature_code":"PPL",
    "gn:name":"Misi",
    "gn:population":0,
    "gn:timezone":"Africa/Blantyre",
    "iso:country":"MW",
    "wof:name":"Misi",
    "wof:placetype":"locality"
},
  "geometry": {"coordinates":[35.71667,-14.96667],"type":"Point"}
}