{
  "type": "Feature",
  "properties": {
    "gn:admin1_code":"S",
    "gn:admin2_code":"2.0",
    "gn:asciiname":"Macikika",
    "gn:country_code":"MW",
    "gn:dem":55,
    "gn:feature_class":"P",
    "gn:feature_code":"PPL",
    "gn:name":"Macikika",
    "gn:population":0,
    "gn:timezone":"Africa/Blantyre",
    "iso:country":"MW",
    "wof:name":"Macikika",
    "wof:placetype":"locality"
},
  "geometry": {"coordinates":[35.01667,-16.48333],"type":"Point"}
}