{
  "type": "Feature",
  "properties": {
    "gn:admin1_code":"S",
    "gn:admin2_code":"25.0",
    "gn:asciiname":"Ngadziwe",
    "gn:country_code":"MW",
    "gn:dem":591,
    "gn:feature_class":"P",
    "gn:feature_code":"PPL",
    "gn:name":"Ngadziwe",
    "gn:population":0,
    "gn:timezone":"Africa/Blantyre",
    "iso:country":"MW",
    "wof:name":"Ngadziwe",
    "wof:placetype":"locality"
},
  "geometry": {"coordinates":[34.5585,-15.78838],"type":"Point"}
}