{
  "type": "Feature",
  "properties": {
    "gn:admin1_code":"C",
    "gn:admin2_code":"11.0",
    "gn:asciiname":"Mpokosa",
    "gn:country_code":"MW",
    "gn:dem":1163,
    "gn:feature_class":"P",
    "gn:feature_code":"PPL",
    "gn:name":"Mpokosa",
    "gn:population":0,
    "gn:timezone":"Africa/Blantyre",
    "iso:country":"MW",
    "wof:name":"Mpokosa",
    "wof:placetype":"locality"
},
  "geometry": {"coordinates":[33.88333,-14.16667],"type":"Point"}
}