{
  "type": "Feature",
  "properties": {
    "gn:admin1_code":"S",
    "gn:admin2_code":"19.0",
    "gn:asciiname":"Nsamba Kulira",
    "gn:country_code":"MW",
    "gn:dem":57,
    "gn:feature_class":"P",
    "gn:feature_code":"PPL",
    "gn:name":"Nsamba Kulira",
    "gn:population":0,
    "gn:timezone":"Africa/Blantyre",
    "iso:country":"MW",
    "wof:name":"Nsamba Kulira",
    "wof:placetype":"locality"
},
  "geometry": {"coordinates":[35.16667,-16.45],"type":"Point"}
}