{
  "type": "Feature",
  "properties": {
    "gn:admin1_code":"S",
    "gn:admin2_code":"30.0",
    "gn:asciiname":"Namasoko",
    "gn:country_code":"MW",
    "gn:dem":717,
    "gn:feature_class":"P",
    "gn:feature_code":"PPL",
    "gn:name":"Namasoko",
    "gn:population":0,
    "gn:timezone":"Africa/Blantyre",
    "iso:country":"MW",
    "wof:name":"Namasoko",
    "wof:placetype":"locality"
},
  "geometry": {"coordinates":[35.61037,-15.69637],"type":"Point"}
}