{
  "type": "Feature",
  "properties": {
    "gn:admin1_code":"C",
    "gn:admin2_code":"20.0",
    "gn:asciiname":"Kapolo",
    "gn:country_code":"MW",
    "gn:dem":690,
    "gn:feature_class":"P",
    "gn:feature_code":"PPL",
    "gn:name":"Kapolo",
    "gn:population":0,
    "gn:timezone":"Africa/Blantyre",
    "iso:country":"MW",
    "wof:name":"Kapolo",
    "wof:placetype":"locality"
},
  "geometry": {"coordinates":[34.08803,-13.30815],"type":"Point"}
}